[
  {
    "id": 1313,
    "date": "2026-07-19",
    "time": "2026-07-19 20:00:31",
    "channel": "@ARKBULLETIN_CN",
    "title": "新游戏内公告：时代系列新装限时上架\n#活动通知",
    "text": "新游戏内公告：时代系列新装限时上架\n#活动通知",
    "content": "新游戏内公告：时代系列新装限时上架\n#活动通知",
    "image": "https://cora.jackie3137.xyz/f/adabd0ce5422ff430633/Thunder%20File%20To%20Link_20260719200032.jpg",
    "images": [
      "https://cora.jackie3137.xyz/f/adabd0ce5422ff430633/Thunder%20File%20To%20Link_20260719200032.jpg"
    ],
    "videos": [],
    "category": "活动",
    "important": false,
    "pinOrder": 999999,
    "pinExpiry": ""
  },
  {
    "id": 16165,
    "date": "2026-07-19",
    "time": "2026-07-19 17:13:05",
    "channel": "@ANIME_NEWS_LATEST",
    "title": "💫\"JUMP FESTA 2027\" is scheduled for December 19 an",
    "text": "💫\"JUMP FESTA 2027\" is scheduled for December 19 and 20 in Japan.💫",
    "content": "💫\"JUMP FESTA 2027\" is scheduled for December 19 and 20 in Japan.💫",
    "image": "https://cora.jackie3137.xyz/f/df79ffb9e912512f1004/Thunder%20File%20To%20Link_20260719171307.jpg",
    "images": [
      "https://cora.jackie3137.xyz/f/df79ffb9e912512f1004/Thunder%20File%20To%20Link_20260719171307.jpg"
    ],
    "videos": [],
    "category": "预告资讯",
    "important": false,
    "pinOrder": 999999,
    "pinExpiry": ""
  },
  {
    "id": 853,
    "date": "2026-07-19",
    "time": "2026-07-19 12:59:15",
    "channel": "@ARKTIPS",
    "title": "26.7.19\nmaa已经支持黑黑流树海存钱",
    "text": "26.7.19\nmaa已经支持黑黑流树海存钱",
    "content": "26.7.19\nmaa已经支持黑黑流树海存钱",
    "image": "https://cora.jackie3137.xyz/f/7437a9ca89d088bc23b5/Thunder%20File%20To%20Link_20260719125916.jpg",
    "images": [
      "https://cora.jackie3137.xyz/f/7437a9ca89d088bc23b5/Thunder%20File%20To%20Link_20260719125916.jpg"
    ],
    "videos": [],
    "category": "活动",
    "important": false,
    "pinOrder": 999999,
    "pinExpiry": ""
  },
  {
    "id": 16164,
    "date": "2026-07-19",
    "time": "2026-07-19 10:21:39",
    "channel": "@ANIME_NEWS_LATEST",
    "title": "💫\"Sometimes Even Reality Is a Lie!\" TV Anime Annou",
    "text": "💫\"Sometimes Even Reality Is a Lie!\" TV Anime Announced.💫\n\nBroadcasting begins in 2027.",
    "content": "💫\"Sometimes Even Reality Is a Lie!\" TV Anime Announced.💫\n\nBroadcasting begins in 2027.",
    "image": "https://cora.jackie3137.xyz/f/f0809ce31d0e1abe1d7a/Thunder%20File%20To%20Link_20260719102141.jpg",
    "images": [
      "https://cora.jackie3137.xyz/f/f0809ce31d0e1abe1d7a/Thunder%20File%20To%20Link_20260719102141.jpg"
    ],
    "videos": [],
    "category": "预告资讯",
    "important": false,
    "pinOrder": 999999,
    "pinExpiry": ""
  },
  {
    "id": 130198,
    "date": "2026-07-19",
    "time": "2026-07-19 10:04:09",
    "channel": "@REVERSE1999CN",
    "title": "#重返未来1999# #重返未来原子之心联动# #重返未来联动# ▶▶轮换征集更新预告◀◀ 「为什么",
    "text": "#重返未来1999# #重返未来原子之心联动# #重返未来联动# ▶▶轮换征集更新预告◀◀ 「为什么故事集」轮换征集将于「振鸣何去从」轮换征集结束后开启，六星星灵感...\n\n#重返未来1999# #重返未来原子之心联动# #重返未来联动# \n▶▶轮换征集更新预告◀◀\n「为什么故事集」轮换征集将于「振鸣何去从」轮换征集结束后开启，六星星灵感角色【纸信圈儿】受邀概率UP！\n\n▶▶征集开放时间◀◀\n7/21 5:00 - 8/4 4:59\n\n▶▶UP角色◀◀\n★★★★★★：纸信圈儿（星）\n★★★★★：讣告人（岩）、命名日（岩）\n\n▶▶征集说明◀◀\n※以上角色的征集受邀概率将大幅提升。\n※轮换征集属于【限时角色征集】，征集保底次数将会与同类征集完全共享，同时累积次数而增加的受邀概率，也会继承至后续的限时角色征集活动。\n※可在游戏内点击征集界面左下角【详情】按钮，查询更多征集信息。\n※该轮换征集尚未包含3.6版本的角色。     收起 查看大图 向左旋转 向右旋转           \n        重返未来：1999\n       \n          游戏\n         \n          角色扮演/策略/卡牌\n         \n        3.8活动剧情《世纪末尺度》正式上映！注册送超100抽及自选范围六星角色\n       \n        进入\n       \n\n专栏链接：https://www.bilibili.com/opus/1226714817337753605",
    "content": "#重返未来1999# #重返未来原子之心联动# #重返未来联动# ▶▶轮换征集更新预告◀◀ 「为什么故事集」轮换征集将于「振鸣何去从」轮换征集结束后开启，六星星灵感...\n\n#重返未来1999# #重返未来原子之心联动# #重返未来联动# \n▶▶轮换征集更新预告◀◀\n「为什么故事集」轮换征集将于「振鸣何去从」轮换征集结束后开启，六星星灵感角色【纸信圈儿】受邀概率UP！\n\n▶▶征集开放时间◀◀\n7/21 5:00 - 8/4 4:59\n\n▶▶UP角色◀◀\n★★★★★★：纸信圈儿（星）\n★★★★★：讣告人（岩）、命名日（岩）\n\n▶▶征集说明◀◀\n※以上角色的征集受邀概率将大幅提升。\n※轮换征集属于【限时角色征集】，征集保底次数将会与同类征集完全共享，同时累积次数而增加的受邀概率，也会继承至后续的限时角色征集活动。\n※可在游戏内点击征集界面左下角【详情】按钮，查询更多征集信息。\n※该轮换征集尚未包含3.6版本的角色。     收起 查看大图 向左旋转 向右旋转           \n        重返未来：1999\n       \n          游戏\n         \n          角色扮演/策略/卡牌\n         \n        3.8活动剧情《世纪末尺度》正式上映！注册送超100抽及自选范围六星角色\n       \n        进入\n       \n\n专栏链接：https://www.bilibili.com/opus/1226714817337753605",
    "image": "https://cora.jackie3137.xyz/f/d62f1bf6328c6db64835/Thunder%20File%20To%20Link_20260719100420.jpg",
    "images": [
      "https://cora.jackie3137.xyz/f/d62f1bf6328c6db64835/Thunder%20File%20To%20Link_20260719100420.jpg",
      "https://cora.jackie3137.xyz/f/1a147786d9ce35ae8c35/Thunder%20File%20To%20Link_20260717100229.jpg"
    ],
    "videos": [],
    "category": "活动",
    "important": false,
    "pinOrder": 999999,
    "pinExpiry": ""
  },
  {
    "id": 130199,
    "date": "2026-07-19",
    "time": "2026-07-19 10:04:38",
    "channel": "@REVERSE1999CN",
    "title": "重返未来1999\n\n#重返未来1999# #重返未来原子之心联动# #重返未来联动# \n▶▶轮换征集",
    "text": "重返未来1999\n\n#重返未来1999# #重返未来原子之心联动# #重返未来联动# \n▶▶轮换征集更新预告◀◀\n「为什么故事集」轮换征集将于「振鸣何去从」轮换征集结束后开启，六星星灵感角色【纸信圈儿】受邀概率UP！\n\n▶▶征集开放时间◀◀\n7/21 5:00 - 8/4 4:59\n\n▶▶UP角色◀◀\n★★★★★★：纸信圈儿（星）\n★★★★★：讣告人（岩）、命名日（岩）\n\n▶▶征集说明◀◀\n※以上角色的征集受邀概率将大幅提升。\n※轮换征集属于【限时角色征集】，征集保底次数将会与同类征集完全共享，同时累积次数而增加的受邀概率，也会继承至后续的限时角色征集活动。\n※可在游戏内点击征集界面左下角【详情】按钮，查询更多征集信息。\n※该轮换征集尚未包含3.6版本的角色。\n\n\n图文地址：https://www.bilibili.com/opus/1226714817337753605",
    "content": "重返未来1999\n\n#重返未来1999# #重返未来原子之心联动# #重返未来联动# \n▶▶轮换征集更新预告◀◀\n「为什么故事集」轮换征集将于「振鸣何去从」轮换征集结束后开启，六星星灵感角色【纸信圈儿】受邀概率UP！\n\n▶▶征集开放时间◀◀\n7/21 5:00 - 8/4 4:59\n\n▶▶UP角色◀◀\n★★★★★★：纸信圈儿（星）\n★★★★★：讣告人（岩）、命名日（岩）\n\n▶▶征集说明◀◀\n※以上角色的征集受邀概率将大幅提升。\n※轮换征集属于【限时角色征集】，征集保底次数将会与同类征集完全共享，同时累积次数而增加的受邀概率，也会继承至后续的限时角色征集活动。\n※可在游戏内点击征集界面左下角【详情】按钮，查询更多征集信息。\n※该轮换征集尚未包含3.6版本的角色。\n\n\n图文地址：https://www.bilibili.com/opus/1226714817337753605",
    "image": "https://cora.jackie3137.xyz/f/8a7b0d19697bc5014cbc/Thunder%20File%20To%20Link_20260719100512.jpg",
    "images": [
      "https://cora.jackie3137.xyz/f/8a7b0d19697bc5014cbc/Thunder%20File%20To%20Link_20260719100512.jpg"
    ],
    "videos": [],
    "category": "活动",
    "important": false,
    "pinOrder": 999999,
    "pinExpiry": ""
  },
  {
    "id": 130195,
    "date": "2026-07-19",
    "time": "2026-07-19 09:00:17",
    "channel": "@REVERSE1999CN",
    "title": "#重返未来1999# 《重返未来：1999》线下小型玩家见面会「箱中茶话会」招募正式开启！ 在本次见",
    "text": "#重返未来1999# 《重返未来：1999》线下小型玩家见面会「箱中茶话会」招募正式开启！ 在本次见面会中，我们将带来制作开发思路、未来版本规划等分享。制作组核心...\n\n#重返未来1999#  \n《重返未来：1999》线下小型玩家见面会「箱中茶话会」招募正式开启！\n\n在本次见面会中，我们将带来制作开发思路、未来版本规划等分享。制作组核心的策划及运营团队成员也将与现场司辰面对面交流，倾听记录大家提出的反馈与建议。此外，在活动中我们也准备了周边伴手礼、趣味小游戏及魔精咖啡茶歇以待司辰光临，期待与大家相聚线下！\n\n▶▶活动详情◀◀\n活动时间：2026年8月8日 14:00~18:00\n举办地点：广州市海珠区·深蓝互动\n报名方式：可通过官方社媒，在招募问卷中填写报名信息\n\n▶▶重要说明◀◀\n1、本次活动为广州线下的小型见面会，需要司辰亲临现场参与。\n2、出于安全考虑，参与本次见面会的司辰需要年满18周岁。\n3、我们预计将于7月30日~7月31日期间，通过问卷中提交的联系方式与受邀玩家进行联系，并同步详细参与事宜，请确保您在问卷中留下的联系方式准确。\n\n*更多活动详情，请点击长图查看。\n\n——————————————————\n此次「箱中茶话会」，是《重返未来：1999》举办的首次玩家见面会，是我们更深度地收集大家想法的全新形式。无法前来线下的司辰，也可将建议填写在问卷中，不论从何种渠道提交的反馈，我们都将认真收集汇总。以本次见面会为起点，后续我们也会再举办此类线下交流活动，让更多司辰能参与进来，感谢大家的支持！   \n            长图\n               收起 查看大图 向左旋转 向右旋转              \n        重返未来：1999\n       \n          游戏\n         \n          角色扮演/策略/卡牌\n         \n        3.8活动剧情《世纪末尺度》正式上映！注册送超100抽及自选范围六星角色\n       \n        进入\n       \n\n专栏链接：https://www.bilibili.com/opus/1226699355480653825",
    "content": "#重返未来1999# 《重返未来：1999》线下小型玩家见面会「箱中茶话会」招募正式开启！ 在本次见面会中，我们将带来制作开发思路、未来版本规划等分享。制作组核心...\n\n#重返未来1999#  \n《重返未来：1999》线下小型玩家见面会「箱中茶话会」招募正式开启！\n\n在本次见面会中，我们将带来制作开发思路、未来版本规划等分享。制作组核心的策划及运营团队成员也将与现场司辰面对面交流，倾听记录大家提出的反馈与建议。此外，在活动中我们也准备了周边伴手礼、趣味小游戏及魔精咖啡茶歇以待司辰光临，期待与大家相聚线下！\n\n▶▶活动详情◀◀\n活动时间：2026年8月8日 14:00~18:00\n举办地点：广州市海珠区·深蓝互动\n报名方式：可通过官方社媒，在招募问卷中填写报名信息\n\n▶▶重要说明◀◀\n1、本次活动为广州线下的小型见面会，需要司辰亲临现场参与。\n2、出于安全考虑，参与本次见面会的司辰需要年满18周岁。\n3、我们预计将于7月30日~7月31日期间，通过问卷中提交的联系方式与受邀玩家进行联系，并同步详细参与事宜，请确保您在问卷中留下的联系方式准确。\n\n*更多活动详情，请点击长图查看。\n\n——————————————————\n此次「箱中茶话会」，是《重返未来：1999》举办的首次玩家见面会，是我们更深度地收集大家想法的全新形式。无法前来线下的司辰，也可将建议填写在问卷中，不论从何种渠道提交的反馈，我们都将认真收集汇总。以本次见面会为起点，后续我们也会再举办此类线下交流活动，让更多司辰能参与进来，感谢大家的支持！   \n            长图\n               收起 查看大图 向左旋转 向右旋转              \n        重返未来：1999\n       \n          游戏\n         \n          角色扮演/策略/卡牌\n         \n        3.8活动剧情《世纪末尺度》正式上映！注册送超100抽及自选范围六星角色\n       \n        进入\n       \n\n专栏链接：https://www.bilibili.com/opus/1226699355480653825",
    "image": "https://cora.jackie3137.xyz/f/d76fbadff0ced4a13815/Thunder%20File%20To%20Link_20260719090032.jpg",
    "images": [
      "https://cora.jackie3137.xyz/f/d76fbadff0ced4a13815/Thunder%20File%20To%20Link_20260719090032.jpg",
      "https://cora.jackie3137.xyz/f/942697f5dbda52778e8d/Thunder%20File%20To%20Link_20260719090122.jpg",
      "https://cora.jackie3137.xyz/f/9024618a655fe60ad9ac/Thunder%20File%20To%20Link_20260719090312.jpg",
      "https://cora.jackie3137.xyz/f/a2afaaddbd4850caac50/Thunder%20File%20To%20Link_20260719090402.jpg",
      "https://cora.jackie3137.xyz/f/1a147786d9ce35ae8c35/Thunder%20File%20To%20Link_20260717100229.jpg"
    ],
    "videos": [],
    "category": "活动",
    "important": false,
    "pinOrder": 999999,
    "pinExpiry": ""
  },
  {
    "id": 130196,
    "date": "2026-07-19",
    "time": "2026-07-19 09:01:34",
    "channel": "@REVERSE1999CN",
    "title": "重返未来1999\n\n#重返未来1999#  \n《重返未来：1999》线下小型玩家见面会「箱中茶话会」",
    "text": "重返未来1999\n\n#重返未来1999#  \n《重返未来：1999》线下小型玩家见面会「箱中茶话会」招募正式开启！\n\n在本次见面会中，我们将带来制作开发思路、未来版本规划等分享。制作组核心的策划及运营团队成员也将与现场司辰面对面交流，倾听记录大家提出的反馈与建议。此外，在活动中我们也准备了周边伴手礼、趣味小游戏及魔精咖啡茶歇以待司辰光临，期待与大家相聚线下！\n\n▶▶活动详情◀◀\n活动时间：2026年8月8日 14:00~18:00\n举办地点：广州市海珠区·深蓝互动\n报名方式：可通过官方社媒，在招募问卷中填写报名信息\n\n▶▶重要说明◀◀\n1、本次活动为广州线下的小型见面会，需要司辰亲临现场参与。\n2、出于安全考虑，参与本次见面会的司辰需要年满18周岁。\n3、我们预计将于7月30日~7月31日期间，通过问卷中提交的联系方式与受邀玩家进行联系，并同步详细参与事宜，请确保您在问卷中留下的联系方式准确。\n\n*更多活动详情，请点击长图查看。\n\n——————————————————\n此次「箱中茶话会」，是《重返未来：1999》举办的首次玩家见面会，是我们更深度地收集大家想法的全新形式。无法前来线下的司辰，也可将建议填写在问卷中，不论从何种渠道提交的反馈，我们都将认真收集汇总。以本次见面会为起点，后续我们也会再举办此类线下交流活动，让更多司辰能参与进来，感谢大家的支持！\n\n\n图文地址：https://www.bilibili.com/opus/1226699355480653825",
    "content": "重返未来1999\n\n#重返未来1999#  \n《重返未来：1999》线下小型玩家见面会「箱中茶话会」招募正式开启！\n\n在本次见面会中，我们将带来制作开发思路、未来版本规划等分享。制作组核心的策划及运营团队成员也将与现场司辰面对面交流，倾听记录大家提出的反馈与建议。此外，在活动中我们也准备了周边伴手礼、趣味小游戏及魔精咖啡茶歇以待司辰光临，期待与大家相聚线下！\n\n▶▶活动详情◀◀\n活动时间：2026年8月8日 14:00~18:00\n举办地点：广州市海珠区·深蓝互动\n报名方式：可通过官方社媒，在招募问卷中填写报名信息\n\n▶▶重要说明◀◀\n1、本次活动为广州线下的小型见面会，需要司辰亲临现场参与。\n2、出于安全考虑，参与本次见面会的司辰需要年满18周岁。\n3、我们预计将于7月30日~7月31日期间，通过问卷中提交的联系方式与受邀玩家进行联系，并同步详细参与事宜，请确保您在问卷中留下的联系方式准确。\n\n*更多活动详情，请点击长图查看。\n\n——————————————————\n此次「箱中茶话会」，是《重返未来：1999》举办的首次玩家见面会，是我们更深度地收集大家想法的全新形式。无法前来线下的司辰，也可将建议填写在问卷中，不论从何种渠道提交的反馈，我们都将认真收集汇总。以本次见面会为起点，后续我们也会再举办此类线下交流活动，让更多司辰能参与进来，感谢大家的支持！\n\n\n图文地址：https://www.bilibili.com/opus/1226699355480653825",
    "image": "https://cora.jackie3137.xyz/f/69ad7eee894ff242efba/Thunder%20File%20To%20Link_20260719090212.jpg",
    "images": [
      "https://cora.jackie3137.xyz/f/69ad7eee894ff242efba/Thunder%20File%20To%20Link_20260719090212.jpg"
    ],
    "videos": [],
    "category": "活动",
    "important": false,
    "pinOrder": 999999,
    "pinExpiry": ""
  },
  {
    "id": 8069,
    "date": "2026-07-19",
    "time": "2026-07-19 04:48:11",
    "channel": "@MCKURO",
    "title": "《星炬不熄》 | 《鸣潮》演唱会「致予新世界」\n\n“让温柔归还天地，\n让终章化作序曲，\n延续，广阔的",
    "text": "《星炬不熄》 | 《鸣潮》演唱会「致予新世界」\n\n“让温柔归还天地，\n让终章化作序曲，\n延续，广阔的意义，\n让星炬不熄。”\n\nsource @MCKURO",
    "content": "《星炬不熄》 | 《鸣潮》演唱会「致予新世界」\n\n“让温柔归还天地，\n让终章化作序曲，\n延续，广阔的意义，\n让星炬不熄。”\n\nsource @MCKURO",
    "image": "https://cora.jackie3137.xyz/f/b17c4f3062c611272346/Thunder%20File%20To%20Link_20260719044907.jpg",
    "images": [
      "https://cora.jackie3137.xyz/f/b17c4f3062c611272346/Thunder%20File%20To%20Link_20260719044907.jpg"
    ],
    "videos": [],
    "category": "活动",
    "important": false,
    "pinOrder": 999999,
    "pinExpiry": ""
  },
  {
    "id": 8068,
    "date": "2026-07-19",
    "time": "2026-07-19 04:48:07",
    "channel": "@MCKURO",
    "title": "《鸣潮》巡回演唱会「致予新世界」官方录播即将上线\n\n《鸣潮》巡回演唱会「致予新世界」官方录播即将上线",
    "text": "《鸣潮》巡回演唱会「致予新世界」官方录播即将上线\n\n《鸣潮》巡回演唱会「致予新世界」官方录播即将上线bilibili，敬请期待！\n\nsource @MCKURO",
    "content": "《鸣潮》巡回演唱会「致予新世界」官方录播即将上线\n\n《鸣潮》巡回演唱会「致予新世界」官方录播即将上线bilibili，敬请期待！\n\nsource @MCKURO",
    "image": "https://cora.jackie3137.xyz/f/ce5236e5756cf3747578/Thunder%20File%20To%20Link_20260719044808.jpg",
    "images": [
      "https://cora.jackie3137.xyz/f/ce5236e5756cf3747578/Thunder%20File%20To%20Link_20260719044808.jpg"
    ],
    "videos": [],
    "category": "活动",
    "important": false,
    "pinOrder": 999999,
    "pinExpiry": ""
  },
  {
    "id": 130190,
    "date": "2026-07-19",
    "time": "2026-07-19 04:31:10",
    "channel": "@REVERSE1999CN",
    "title": "重返未来1999\n\n#重返未来1999# #重返未来原子之心联动# #重返未来联动# \n//衣着上新",
    "text": "重返未来1999\n\n#重返未来1999# #重返未来原子之心联动# #重返未来联动# \n//衣着上新\n共生花 | Symbiotic Lee-ly\n*装置式未来*系列，泥鯭的士全新衣着。\n一株聚合的成果？应该说，是与之共度时光的家人！\n\n▶▶衣着宣传折页◀◀\n※全新神秘术特效\n※崭新形象\n※全新Live2D交互动作×2\n※全新战斗入场效果\n※全新荒原动作\n※崭新单品×3\n\n▶▶获取途径◀◀\n7/23 10:00 - 8/13 4:59，泥鯭的士新增衣着「共生花」将在【衣着风尚】商店上架并限时售卖。\n\n\n图文地址：https://www.bilibili.com/opus/1226622046088200211",
    "content": "重返未来1999\n\n#重返未来1999# #重返未来原子之心联动# #重返未来联动# \n//衣着上新\n共生花 | Symbiotic Lee-ly\n*装置式未来*系列，泥鯭的士全新衣着。\n一株聚合的成果？应该说，是与之共度时光的家人！\n\n▶▶衣着宣传折页◀◀\n※全新神秘术特效\n※崭新形象\n※全新Live2D交互动作×2\n※全新战斗入场效果\n※全新荒原动作\n※崭新单品×3\n\n▶▶获取途径◀◀\n7/23 10:00 - 8/13 4:59，泥鯭的士新增衣着「共生花」将在【衣着风尚】商店上架并限时售卖。\n\n\n图文地址：https://www.bilibili.com/opus/1226622046088200211",
    "image": "https://cora.jackie3137.xyz/f/1f6137c35536c76591f5/Thunder%20File%20To%20Link_20260719043355.jpg",
    "images": [
      "https://cora.jackie3137.xyz/f/1f6137c35536c76591f5/Thunder%20File%20To%20Link_20260719043355.jpg",
      "https://cora.jackie3137.xyz/f/051859d1be8bf9f43c08/Thunder%20File%20To%20Link_20260719043741.jpg",
      "https://cora.jackie3137.xyz/f/58102ae32aa2915dc021/Thunder%20File%20To%20Link_20260719043832.jpg",
      "https://cora.jackie3137.xyz/f/b9ad425f7dd0257668e4/Thunder%20File%20To%20Link_20260719043922.jpg",
      "https://cora.jackie3137.xyz/f/d6900a60ff45e1918912/Thunder%20File%20To%20Link_20260719044012.jpg",
      "https://cora.jackie3137.xyz/f/645fade6cad6a6099067/Thunder%20File%20To%20Link_20260719044102.jpg",
      "https://cora.jackie3137.xyz/f/5b6c8fa60fb5b51b2544/Thunder%20File%20To%20Link_20260719044153.jpg",
      "https://cora.jackie3137.xyz/f/db3530ca5f76e0b2a79c/Thunder%20File%20To%20Link_20260719044243.jpg",
      "https://cora.jackie3137.xyz/f/2878c42fb1410e725ded/Thunder%20File%20To%20Link_20260719044333.jpg"
    ],
    "videos": [],
    "category": "活动",
    "important": false,
    "pinOrder": 999999,
    "pinExpiry": ""
  },
  {
    "id": 130181,
    "date": "2026-07-19",
    "time": "2026-07-19 04:02:54",
    "channel": "@REVERSE1999CN",
    "title": "#重返未来1999# #重返未来原子之心联动# #重返未来联动# //衣着上新 共生花 | Symb",
    "text": "#重返未来1999# #重返未来原子之心联动# #重返未来联动# //衣着上新 共生花 | Symbiotic Lee-ly *装置式未来*系列，泥鯭的士全新衣着。 一株聚合的成果？应该说...\n\n#重返未来1999# #重返未来原子之心联动# #重返未来联动# \n//衣着上新\n共生花 | Symbiotic Lee-ly\n*装置式未来*系列，泥鯭的士全新衣着。\n一株聚合的成果？应该说，是与之共度时光的家人！\n\n▶▶衣着宣传折页◀◀\n※全新神秘术特效\n※崭新形象\n※全新Live2D交互动作×2\n※全新战斗入场效果\n※全新荒原动作\n※崭新单品×3\n\n▶▶获取途径◀◀\n7/23 10:00 - 8/13 4:59，泥鯭的士新增衣着「共生花」将在【衣着风尚】商店上架并限时售卖。   \n            动图\n             \n            动图\n                \n            动图\n             \n            动图\n             \n            动图\n             \n            动图\n             \n            动图\n               收起 查看大图 向左旋转 向右旋转              \n        重返未来：1999\n       \n          游戏\n         \n          角色扮演/策略/卡牌\n         \n        3.8活动剧情《世纪末尺度》正式上映！注册送超100抽及自选范围六星角色\n       \n        进入\n       \n\n专栏链接：https://www.bilibili.com/opus/1226622046088200211",
    "content": "#重返未来1999# #重返未来原子之心联动# #重返未来联动# //衣着上新 共生花 | Symbiotic Lee-ly *装置式未来*系列，泥鯭的士全新衣着。 一株聚合的成果？应该说...\n\n#重返未来1999# #重返未来原子之心联动# #重返未来联动# \n//衣着上新\n共生花 | Symbiotic Lee-ly\n*装置式未来*系列，泥鯭的士全新衣着。\n一株聚合的成果？应该说，是与之共度时光的家人！\n\n▶▶衣着宣传折页◀◀\n※全新神秘术特效\n※崭新形象\n※全新Live2D交互动作×2\n※全新战斗入场效果\n※全新荒原动作\n※崭新单品×3\n\n▶▶获取途径◀◀\n7/23 10:00 - 8/13 4:59，泥鯭的士新增衣着「共生花」将在【衣着风尚】商店上架并限时售卖。   \n            动图\n             \n            动图\n                \n            动图\n             \n            动图\n             \n            动图\n             \n            动图\n             \n            动图\n               收起 查看大图 向左旋转 向右旋转              \n        重返未来：1999\n       \n          游戏\n         \n          角色扮演/策略/卡牌\n         \n        3.8活动剧情《世纪末尺度》正式上映！注册送超100抽及自选范围六星角色\n       \n        进入\n       \n\n专栏链接：https://www.bilibili.com/opus/1226622046088200211",
    "image": "https://cora.jackie3137.xyz/f/278ae92d4c02957a475b/Thunder%20File%20To%20Link_20260719040557.jpg",
    "images": [
      "https://cora.jackie3137.xyz/f/278ae92d4c02957a475b/Thunder%20File%20To%20Link_20260719040557.jpg",
      "https://cora.jackie3137.xyz/f/6561f439fd8dd5c9f11b/Thunder%20File%20To%20Link_20260719041008.jpg",
      "https://cora.jackie3137.xyz/f/60d5eb9aaa1ad31a7b78/Thunder%20File%20To%20Link_20260719041419.jpg",
      "https://cora.jackie3137.xyz/f/f127d84ec4da339f8702/Thunder%20File%20To%20Link_20260719041830.jpg",
      "https://cora.jackie3137.xyz/f/e95de03a2fad962b3a7f/Thunder%20File%20To%20Link_20260719042259.jpg",
      "https://cora.jackie3137.xyz/f/934d47fc46ff8f0fb9a0/Thunder%20File%20To%20Link_20260719042530.jpg",
      "https://cora.jackie3137.xyz/f/40d05a7535f07be468c0/Thunder%20File%20To%20Link_20260719042801.jpg",
      "https://cora.jackie3137.xyz/f/967925c4035d04958a8b/Thunder%20File%20To%20Link_20260719043031.jpg",
      "https://cora.jackie3137.xyz/f/5b4192a4973a01d79a2c/Thunder%20File%20To%20Link_20260719043302.jpg",
      "https://cora.jackie3137.xyz/f/278ae92d4c02957a475b/Thunder%20File%20To%20Link_20260719040557.jpg"
    ],
    "videos": [],
    "category": "活动",
    "important": false,
    "pinOrder": 999999,
    "pinExpiry": ""
  },
  {
    "id": 6726,
    "date": "2026-07-19",
    "time": "2026-07-19 04:02:30",
    "channel": "@YUANSHEN",
    "title": "@YUANSHEN",
    "text": "",
    "content": "",
    "image": "https://cora.jackie3137.xyz/f/d19b13039b34860fe188/Thunder%20File%20To%20Link_20260719040326.jpg",
    "images": [
      "https://cora.jackie3137.xyz/f/d19b13039b34860fe188/Thunder%20File%20To%20Link_20260719040326.jpg",
      "https://cora.jackie3137.xyz/f/48835d4119dec969341f/Thunder%20File%20To%20Link_20260719040737.jpg",
      "https://cora.jackie3137.xyz/f/b6502b20b2497949c98d/Thunder%20File%20To%20Link_20260719041149.jpg",
      "https://cora.jackie3137.xyz/f/9f73f7d48ca4d9f5a54d/Thunder%20File%20To%20Link_20260719041600.jpg",
      "https://cora.jackie3137.xyz/f/0464b5223006b624e7c5/Thunder%20File%20To%20Link_20260719042011.jpg",
      "https://cora.jackie3137.xyz/f/282e24e4aaa5eac1b4fe/Thunder%20File%20To%20Link_20260719042440.jpg",
      "https://cora.jackie3137.xyz/f/e149eee5d8cf957290f1/Thunder%20File%20To%20Link_20260719042711.jpg",
      "https://cora.jackie3137.xyz/f/a12f3c09aa8fc8f8f271/Thunder%20File%20To%20Link_20260719042941.jpg",
      "https://cora.jackie3137.xyz/f/566975dbe074502a9a24/Thunder%20File%20To%20Link_20260719043212.jpg",
      "https://cora.jackie3137.xyz/f/63ab7aa5f296fe18a93b/Thunder%20File%20To%20Link_20260719043544.jpg"
    ],
    "videos": [],
    "category": "活动",
    "important": false,
    "pinOrder": 999999,
    "pinExpiry": ""
  },
  {
    "id": 6716,
    "date": "2026-07-19",
    "time": "2026-07-19 04:02:24",
    "channel": "@YUANSHEN",
    "title": "@YUANSHEN",
    "text": "",
    "content": "",
    "image": "https://cora.jackie3137.xyz/f/7a5cc4f3669b6418d69d/Thunder%20File%20To%20Link_20260719040236.jpg",
    "images": [
      "https://cora.jackie3137.xyz/f/7a5cc4f3669b6418d69d/Thunder%20File%20To%20Link_20260719040236.jpg",
      "https://cora.jackie3137.xyz/f/c8091a2fb84cbd5e4914/Thunder%20File%20To%20Link_20260719040647.jpg",
      "https://cora.jackie3137.xyz/f/aaf28f48860340454bb5/Thunder%20File%20To%20Link_20260719041058.jpg",
      "https://cora.jackie3137.xyz/f/9f354d3670baee7ddbbf/Thunder%20File%20To%20Link_20260719041510.jpg",
      "https://cora.jackie3137.xyz/f/c6afb1c4be3c7a171c42/Thunder%20File%20To%20Link_20260719041921.jpg",
      "https://cora.jackie3137.xyz/f/7e3b0413a18a3687d171/Thunder%20File%20To%20Link_20260719042349.jpg",
      "https://cora.jackie3137.xyz/f/f87d126fe5e65cde0221/Thunder%20File%20To%20Link_20260719042620.jpg",
      "https://cora.jackie3137.xyz/f/12271a55a7a9a92ea28a/Thunder%20File%20To%20Link_20260719042851.jpg",
      "https://cora.jackie3137.xyz/f/39b98ad92cdb11bf2725/Thunder%20File%20To%20Link_20260719043122.jpg",
      "https://cora.jackie3137.xyz/f/f71c5ca13b374335623f/Thunder%20File%20To%20Link_20260719043445.jpg"
    ],
    "videos": [],
    "category": "活动",
    "important": false,
    "pinOrder": 999999,
    "pinExpiry": ""
  },
  {
    "id": 6736,
    "date": "2026-07-19",
    "time": "2026-07-19 04:02:46",
    "channel": "@YUANSHEN",
    "title": "理论上「雷电将军」能复制影的一切，但… |「雷电将军」·侧记\n\n旅行者好呀！「影寂天下人」祈愿将于7",
    "text": "理论上「雷电将军」能复制影的一切，但… |「雷电将军」·侧记\n\n旅行者好呀！「影寂天下人」祈愿将于7月21日18:00开启，届时，「一心净土·雷电将军」的获取概率将大幅提升。\n「『幻』如浮世，『寂』乃本质，其身为御建鸣神主尊大御所大人。」\n点击了解更多「月之八」版本内容：\n>>原神「『空月之歌·谐谑』映夏！归乡？千灵节！」内容专题页<<\n\nsource @YuanShen",
    "content": "理论上「雷电将军」能复制影的一切，但… |「雷电将军」·侧记\n\n旅行者好呀！「影寂天下人」祈愿将于7月21日18:00开启，届时，「一心净土·雷电将军」的获取概率将大幅提升。\n「『幻』如浮世，『寂』乃本质，其身为御建鸣神主尊大御所大人。」\n点击了解更多「月之八」版本内容：\n>>原神「『空月之歌·谐谑』映夏！归乡？千灵节！」内容专题页<<\n\nsource @YuanShen",
    "image": "https://cora.jackie3137.xyz/f/f920aa4e33bafcd5195f/Thunder%20File%20To%20Link_20260719040506.jpg",
    "images": [
      "https://cora.jackie3137.xyz/f/f920aa4e33bafcd5195f/Thunder%20File%20To%20Link_20260719040506.jpg",
      "https://cora.jackie3137.xyz/f/c109f7a2b4f524cffea8/Thunder%20File%20To%20Link_20260719040918.jpg",
      "https://cora.jackie3137.xyz/f/cc07d22225cff0d0d260/Thunder%20File%20To%20Link_20260719041329.jpg",
      "https://cora.jackie3137.xyz/f/7031a8d03dfd53d42480/Thunder%20File%20To%20Link_20260719041740.jpg",
      "https://cora.jackie3137.xyz/f/fcc98bdf66db972e40a7/Thunder%20File%20To%20Link_20260719042200.jpg"
    ],
    "videos": [],
    "category": "活动",
    "important": false,
    "pinOrder": 999999,
    "pinExpiry": ""
  },
  {
    "id": 6731,
    "date": "2026-07-19",
    "time": "2026-07-19 04:02:39",
    "channel": "@YUANSHEN",
    "title": "《原神》「星稚梦旅系列」周边贩售即将开启\n\n亲爱的旅行者，《原神》「星稚梦旅系列」周边特别企划全品类",
    "text": "《原神》「星稚梦旅系列」周边贩售即将开启\n\n亲爱的旅行者，《原神》「星稚梦旅系列」周边特别企划全品类正式亮相，即将于7月22日20:00在原神官方周边店铺开启贩售！\n本次带来的商品有：徽章、多插立牌、镜面手机挂绳、Q版仿糖葫芦徽章串、折叠扇、Q版盒装木质印章、亚克力收纳盒、文件袋贴纸包套组，将旅行伙伴的童年模样珍藏~\n目前该系列新品已开放预览，旅行者可前往店内查看详情。\n8月中旬起，星稚梦旅系列还将会在线下指定渠道开启特别的互动活动哦，旅行者敬请留意后续资讯，一起期待吧~\n\nsource @YuanShen",
    "content": "《原神》「星稚梦旅系列」周边贩售即将开启\n\n亲爱的旅行者，《原神》「星稚梦旅系列」周边特别企划全品类正式亮相，即将于7月22日20:00在原神官方周边店铺开启贩售！\n本次带来的商品有：徽章、多插立牌、镜面手机挂绳、Q版仿糖葫芦徽章串、折叠扇、Q版盒装木质印章、亚克力收纳盒、文件袋贴纸包套组，将旅行伙伴的童年模样珍藏~\n目前该系列新品已开放预览，旅行者可前往店内查看详情。\n8月中旬起，星稚梦旅系列还将会在线下指定渠道开启特别的互动活动哦，旅行者敬请留意后续资讯，一起期待吧~\n\nsource @YuanShen",
    "image": "https://cora.jackie3137.xyz/f/098dfbeb112dbc33d183/Thunder%20File%20To%20Link_20260719040416.jpg",
    "images": [
      "https://cora.jackie3137.xyz/f/098dfbeb112dbc33d183/Thunder%20File%20To%20Link_20260719040416.jpg",
      "https://cora.jackie3137.xyz/f/38cc7eae789327008d53/Thunder%20File%20To%20Link_20260719040828.jpg",
      "https://cora.jackie3137.xyz/f/f7e52564e4586896f8b7/Thunder%20File%20To%20Link_20260719041239.jpg",
      "https://cora.jackie3137.xyz/f/a5038b0ff37a23ec02c5/Thunder%20File%20To%20Link_20260719041650.jpg",
      "https://cora.jackie3137.xyz/f/85e57e38a7b3629c6b15/Thunder%20File%20To%20Link_20260719042101.jpg"
    ],
    "videos": [],
    "category": "活动",
    "important": false,
    "pinOrder": 999999,
    "pinExpiry": ""
  },
  {
    "id": 16163,
    "date": "2026-07-18",
    "time": "2026-07-18 16:27:37",
    "channel": "@ANIME_NEWS_LATEST",
    "title": "@ANIME_NEWS_LATEST",
    "text": "",
    "content": "",
    "image": "https://cora.jackie3137.xyz/f/39d93c5657d6710e554c/%27Wuthering_Waves%3B_Elysium%27_Animated_Series_Reveal%21_1080p_29fps_AV1.mp4",
    "images": [],
    "videos": [
      "https://cora.jackie3137.xyz/f/39d93c5657d6710e554c/%27Wuthering_Waves%3B_Elysium%27_Animated_Series_Reveal%21_1080p_29fps_AV1.mp4"
    ],
    "category": "预告资讯",
    "important": false,
    "pinOrder": 999999,
    "pinExpiry": ""
  },
  {
    "id": 8061,
    "date": "2026-07-18",
    "time": "2026-07-18 15:30:16",
    "channel": "@MCKURO",
    "title": "@MCKURO",
    "text": "",
    "content": "",
    "image": "https://cora.jackie3137.xyz/f/63c4fb51f3a01ceb9232/Thunder%20File%20To%20Link_20260718153028.jpg",
    "images": [
      "https://cora.jackie3137.xyz/f/63c4fb51f3a01ceb9232/Thunder%20File%20To%20Link_20260718153028.jpg",
      "https://cora.jackie3137.xyz/f/1f5d482a7123642542d4/Thunder%20File%20To%20Link_20260718153209.jpg",
      "https://cora.jackie3137.xyz/f/35abf7450d80bfbd6a15/Thunder%20File%20To%20Link_20260718153349.jpg",
      "https://cora.jackie3137.xyz/f/6d97a3d1be8805e5912a/Thunder%20File%20To%20Link_20260718153530.jpg",
      "https://cora.jackie3137.xyz/f/a826ffdb5348fb6ed2ed/Thunder%20File%20To%20Link_20260718153710.jpg",
      "https://cora.jackie3137.xyz/f/685d2d78532cd76d1dd3/Thunder%20File%20To%20Link_20260718153852.jpg",
      "https://cora.jackie3137.xyz/f/23e87db6884339396138/Thunder%20File%20To%20Link_20260718154044.jpg",
      "https://cora.jackie3137.xyz/f/66209ffaff99e19f79f4/Thunder%20File%20To%20Link_20260718154134.jpg",
      "https://cora.jackie3137.xyz/f/d026e550a52222db9cb7/Thunder%20File%20To%20Link_20260718154225.jpg",
      "https://cora.jackie3137.xyz/f/06a6de82f8910123e315/Thunder%20File%20To%20Link_20260718154315.jpg"
    ],
    "videos": [],
    "category": "活动",
    "important": false,
    "pinOrder": 999999,
    "pinExpiry": ""
  },
  {
    "id": 8067,
    "date": "2026-07-18",
    "time": "2026-07-18 15:30:22",
    "channel": "@MCKURO",
    "title": "《鸣潮》巡回演唱会「致予新世界」| 现场返图\n\n演出圆满落幕！\n感谢漂泊者们的一路相伴，期待未来的每",
    "text": "《鸣潮》巡回演唱会「致予新世界」| 现场返图\n\n演出圆满落幕！\n感谢漂泊者们的一路相伴，期待未来的每一次相聚。\n\nsource @MCKURO",
    "content": "《鸣潮》巡回演唱会「致予新世界」| 现场返图\n\n演出圆满落幕！\n感谢漂泊者们的一路相伴，期待未来的每一次相聚。\n\nsource @MCKURO",
    "image": "https://cora.jackie3137.xyz/f/26333979f159b9d9d6cb/Thunder%20File%20To%20Link_20260718153118.jpg",
    "images": [
      "https://cora.jackie3137.xyz/f/26333979f159b9d9d6cb/Thunder%20File%20To%20Link_20260718153118.jpg",
      "https://cora.jackie3137.xyz/f/b4b817c0771a41598a35/Thunder%20File%20To%20Link_20260718153259.jpg",
      "https://cora.jackie3137.xyz/f/3553bb785089f9e06993/Thunder%20File%20To%20Link_20260718153439.jpg",
      "https://cora.jackie3137.xyz/f/dd247e2aaf35fd24ac3c/Thunder%20File%20To%20Link_20260718153620.jpg",
      "https://cora.jackie3137.xyz/f/32332a026b73c361c6ce/Thunder%20File%20To%20Link_20260718153801.jpg",
      "https://cora.jackie3137.xyz/f/47fd5768b951f7067f7e/Thunder%20File%20To%20Link_20260718153944.jpg"
    ],
    "videos": [],
    "category": "活动",
    "important": false,
    "pinOrder": 999999,
    "pinExpiry": ""
  },
  {
    "id": 8051,
    "date": "2026-07-18",
    "time": "2026-07-18 14:30:09",
    "channel": "@MCKURO",
    "title": "《鸣潮》剧集「向彼方行」正式启动！\n\n由库洛游戏旗下动画品牌库洛映迹推出的全新《鸣潮》主题剧集企划「",
    "text": "《鸣潮》剧集「向彼方行」正式启动！\n\n由库洛游戏旗下动画品牌库洛映迹推出的全新《鸣潮》主题剧集企划「向彼方行」正式启动，敬请期待。\n\nsource @MCKURO",
    "content": "《鸣潮》剧集「向彼方行」正式启动！\n\n由库洛游戏旗下动画品牌库洛映迹推出的全新《鸣潮》主题剧集企划「向彼方行」正式启动，敬请期待。\n\nsource @MCKURO",
    "image": "https://cora.jackie3137.xyz/f/624fa783a0139c184d0a/Thunder%20File%20To%20Link_20260718143011.jpg",
    "images": [
      "https://cora.jackie3137.xyz/f/624fa783a0139c184d0a/Thunder%20File%20To%20Link_20260718143011.jpg"
    ],
    "videos": [],
    "category": "活动",
    "important": false,
    "pinOrder": 999999,
    "pinExpiry": ""
  },
  {
    "id": 16162,
    "date": "2026-07-18",
    "time": "2026-07-18 13:54:24",
    "channel": "@ANIME_NEWS_LATEST",
    "title": "💫\"Tune in to the Midnight Heart\" TV Anime Season 2",
    "text": "💫\"Tune in to the Midnight Heart\" TV Anime Season 2 New Visual.💫\n\nBroadcasting begins in 2027.",
    "content": "💫\"Tune in to the Midnight Heart\" TV Anime Season 2 New Visual.💫\n\nBroadcasting begins in 2027.",
    "image": "https://cora.jackie3137.xyz/f/81fcc1262a61a7d1b30e/Thunder%20File%20To%20Link_20260718135425.jpg",
    "images": [
      "https://cora.jackie3137.xyz/f/81fcc1262a61a7d1b30e/Thunder%20File%20To%20Link_20260718135425.jpg"
    ],
    "videos": [],
    "category": "预告资讯",
    "important": false,
    "pinOrder": 999999,
    "pinExpiry": ""
  },
  {
    "id": 8048,
    "date": "2026-07-18",
    "time": "2026-07-18 11:28:07",
    "channel": "@MCKURO",
    "title": "《鸣潮》巡回演唱会「致予新世界」特别活动上线！\n\n参与《鸣潮》巡回演唱会「致予新世界」特别活动，有机",
    "text": "《鸣潮》巡回演唱会「致予新世界」特别活动上线！\n\n参与《鸣潮》巡回演唱会「致予新世界」特别活动，有机会赢取星声、游戏道具、限定勋章等奖励！QQ音乐、酷狗音乐专属限定装扮同步上架！\n\n✦ 活动平台 ✦\n漂泊者可前往【QQ音乐】、【酷狗音乐】搜索【鸣潮】参与活动！\n\n✦ 活动时间 ✦\n即日起至2026年7月31日23:59。\n\n✦ 活动好礼 ✦\n完成页面任务，即有机会领取限定勋章、专属限定陪伴等奖励。\n\n✦ 抽奖活动 ✦\n完成互动任务，更有机会抽取星声等游戏道具奖励。\n\nsource @MCKURO",
    "content": "《鸣潮》巡回演唱会「致予新世界」特别活动上线！\n\n参与《鸣潮》巡回演唱会「致予新世界」特别活动，有机会赢取星声、游戏道具、限定勋章等奖励！QQ音乐、酷狗音乐专属限定装扮同步上架！\n\n✦ 活动平台 ✦\n漂泊者可前往【QQ音乐】、【酷狗音乐】搜索【鸣潮】参与活动！\n\n✦ 活动时间 ✦\n即日起至2026年7月31日23:59。\n\n✦ 活动好礼 ✦\n完成页面任务，即有机会领取限定勋章、专属限定陪伴等奖励。\n\n✦ 抽奖活动 ✦\n完成互动任务，更有机会抽取星声等游戏道具奖励。\n\nsource @MCKURO",
    "image": "https://cora.jackie3137.xyz/f/79b47edfcec820821dc6/Thunder%20File%20To%20Link_20260718112819.jpg",
    "images": [
      "https://cora.jackie3137.xyz/f/79b47edfcec820821dc6/Thunder%20File%20To%20Link_20260718112819.jpg",
      "https://cora.jackie3137.xyz/f/fa0fb980fd968ba0d3db/Thunder%20File%20To%20Link_20260718112909.jpg",
      "https://cora.jackie3137.xyz/f/b3ce4eef313f6186541c/Thunder%20File%20To%20Link_20260718112959.jpg",
      "https://cora.jackie3137.xyz/f/d3f45075e6f9ed83152b/Thunder%20File%20To%20Link_20260718113248.jpg"
    ],
    "videos": [],
    "category": "活动",
    "important": false,
    "pinOrder": 999999,
    "pinExpiry": ""
  },
  {
    "id": 8050,
    "date": "2026-07-18",
    "time": "2026-07-18 11:30:11",
    "channel": "@MCKURO",
    "title": "《昼梦盛宴》 | 《鸣潮》演唱会「致予新世界」\n\n“尽兴吧，灯光为你在聚焦，\n别缄默快歌唱，主角已来",
    "text": "《昼梦盛宴》 | 《鸣潮》演唱会「致予新世界」\n\n“尽兴吧，灯光为你在聚焦，\n别缄默快歌唱，主角已来到。”\n\nsource @MCKURO",
    "content": "《昼梦盛宴》 | 《鸣潮》演唱会「致予新世界」\n\n“尽兴吧，灯光为你在聚焦，\n别缄默快歌唱，主角已来到。”\n\nsource @MCKURO",
    "image": "https://cora.jackie3137.xyz/f/ff1465174fa41e1d49bb/Thunder%20File%20To%20Link_20260718113149.jpg",
    "images": [
      "https://cora.jackie3137.xyz/f/ff1465174fa41e1d49bb/Thunder%20File%20To%20Link_20260718113149.jpg"
    ],
    "videos": [],
    "category": "活动",
    "important": false,
    "pinOrder": 999999,
    "pinExpiry": ""
  },
  {
    "id": 8049,
    "date": "2026-07-18",
    "time": "2026-07-18 11:30:06",
    "channel": "@MCKURO",
    "title": "《愿戴荣光坠入天渊》&《逆潮》 | 《鸣潮》演唱会「致予新世界」\n\n“任风潮重塑这副躯壳，\n随我迈向",
    "text": "《愿戴荣光坠入天渊》&《逆潮》 | 《鸣潮》演唱会「致予新世界」\n\n“任风潮重塑这副躯壳，\n随我迈向将临的曙光。”\n\nsource @MCKURO",
    "content": "《愿戴荣光坠入天渊》&《逆潮》 | 《鸣潮》演唱会「致予新世界」\n\n“任风潮重塑这副躯壳，\n随我迈向将临的曙光。”\n\nsource @MCKURO",
    "image": "https://cora.jackie3137.xyz/f/eadcbce131340aa32c90/Thunder%20File%20To%20Link_20260718113049.jpg",
    "images": [
      "https://cora.jackie3137.xyz/f/eadcbce131340aa32c90/Thunder%20File%20To%20Link_20260718113049.jpg"
    ],
    "videos": [],
    "category": "活动",
    "important": false,
    "pinOrder": 999999,
    "pinExpiry": ""
  },
  {
    "id": 8044,
    "date": "2026-07-18",
    "time": "2026-07-18 11:02:06",
    "channel": "@MCKURO",
    "title": "✦致予新世界·鸣潮巡回演唱会官方直播✦\n\n“我们因共同前行的路途，记住了一段段独特的旋律；也因这些熟",
    "text": "✦致予新世界·鸣潮巡回演唱会官方直播✦\n\n“我们因共同前行的路途，记住了一段段独特的旋律；也因这些熟悉的旋律，于此相聚。”\n此刻，走向新世界。\n致予新世界·鸣潮巡回演唱会官方直播已开始，漂泊者可点击链接观看：致予新世界·鸣潮巡回演唱会\n\nsource @MCKURO",
    "content": "✦致予新世界·鸣潮巡回演唱会官方直播✦\n\n“我们因共同前行的路途，记住了一段段独特的旋律；也因这些熟悉的旋律，于此相聚。”\n此刻，走向新世界。\n致予新世界·鸣潮巡回演唱会官方直播已开始，漂泊者可点击链接观看：致予新世界·鸣潮巡回演唱会\n\nsource @MCKURO",
    "image": "https://cora.jackie3137.xyz/f/82024d3a20acefa001be/Thunder%20File%20To%20Link_20260718110207.jpg",
    "images": [
      "https://cora.jackie3137.xyz/f/82024d3a20acefa001be/Thunder%20File%20To%20Link_20260718110207.jpg"
    ],
    "videos": [],
    "category": "活动",
    "important": false,
    "pinOrder": 999999,
    "pinExpiry": ""
  },
  {
    "id": 130167,
    "date": "2026-07-18",
    "time": "2026-07-18 10:23:00",
    "channel": "@REVERSE1999CN",
    "title": "重返未来1999\n\n#重返未来1999# #重返未来原子之心联动# #重返未来联动# \n【鬃毛邮报】",
    "text": "重返未来1999\n\n#重返未来1999# #重返未来原子之心联动# #重返未来联动# \n【鬃毛邮报】即将开启！\n调查传闻中的离奇事迹，将线索揣进不漏风的兜里。\n我们为最灵通的消息奉上黄金与盛誉。\n\n▶▶活动时间◀◀\n「自我同情者」调查时间：7/23 10:00 - 8/13 4:59\n「信仰的移位·Ⅱ型」调查时间：7/30 5:00 - 8/13 4:59\n「毁灭的履带」调查时间：8/6 5:00 - 8/13 4:59\n\n▶▶开启条件◀◀\n通关主线故事1ST.16「天堂使徒」\n\n▶▶玩法说明◀◀\n※【隐匿度】：根据特殊要求进行削减，削减至0后可进入额外的【目击回合】。削减【隐匿度】还能累计分数，与对首领怪物造成伤害获得的分数一起相加后根据总分评级并记录进【调查进度】中。\n※【目击者等级】：通过在战斗中取得分数来累计经验，提升等级后即可获得奖励。该奖励系统会在后续每次鬃毛邮报开启期间持续累计。\n※【首领图鉴】：收纳了所有首领怪物的信息并可查看“调查建议”。\n\n「自我同情者」薄弱点：星、岩\n「信仰的移位·Ⅱ型」薄弱点：兽、智\n「毁灭的履带 」灵感：星\n\n▶▶主要奖励◀◀\n饕餮、贪欲、共鸣晶匣、悠远的振响、偏振、共鸣材料、洞悉材料\n\n\n图文地址：https://www.bilibili.com/opus/1226343732209516547",
    "content": "重返未来1999\n\n#重返未来1999# #重返未来原子之心联动# #重返未来联动# \n【鬃毛邮报】即将开启！\n调查传闻中的离奇事迹，将线索揣进不漏风的兜里。\n我们为最灵通的消息奉上黄金与盛誉。\n\n▶▶活动时间◀◀\n「自我同情者」调查时间：7/23 10:00 - 8/13 4:59\n「信仰的移位·Ⅱ型」调查时间：7/30 5:00 - 8/13 4:59\n「毁灭的履带」调查时间：8/6 5:00 - 8/13 4:59\n\n▶▶开启条件◀◀\n通关主线故事1ST.16「天堂使徒」\n\n▶▶玩法说明◀◀\n※【隐匿度】：根据特殊要求进行削减，削减至0后可进入额外的【目击回合】。削减【隐匿度】还能累计分数，与对首领怪物造成伤害获得的分数一起相加后根据总分评级并记录进【调查进度】中。\n※【目击者等级】：通过在战斗中取得分数来累计经验，提升等级后即可获得奖励。该奖励系统会在后续每次鬃毛邮报开启期间持续累计。\n※【首领图鉴】：收纳了所有首领怪物的信息并可查看“调查建议”。\n\n「自我同情者」薄弱点：星、岩\n「信仰的移位·Ⅱ型」薄弱点：兽、智\n「毁灭的履带 」灵感：星\n\n▶▶主要奖励◀◀\n饕餮、贪欲、共鸣晶匣、悠远的振响、偏振、共鸣材料、洞悉材料\n\n\n图文地址：https://www.bilibili.com/opus/1226343732209516547",
    "image": "https://cora.jackie3137.xyz/f/6a83fd6e70ddd02445c0/Thunder%20File%20To%20Link_20260718102301.jpg",
    "images": [
      "https://cora.jackie3137.xyz/f/6a83fd6e70ddd02445c0/Thunder%20File%20To%20Link_20260718102301.jpg"
    ],
    "videos": [],
    "category": "活动",
    "important": false,
    "pinOrder": 999999,
    "pinExpiry": ""
  },
  {
    "id": 6706,
    "date": "2026-07-18",
    "time": "2026-07-18 10:02:10",
    "channel": "@YUANSHEN",
    "title": "《原神》星稚梦旅周边特别企划揭晓 系列表情包现已上线\n\n亲爱的旅行者，《原神》全新「星稚梦旅系列」周",
    "text": "《原神》星稚梦旅周边特别企划揭晓 系列表情包现已上线\n\n亲爱的旅行者，《原神》全新「星稚梦旅系列」周边特别企划正式公开，本次与旅行者见面的旅行伙伴有：芙宁娜、达达利亚、菲林斯、钟离、莱欧斯利、哥伦比娅。\n和旅行伙伴一起掠过童年的光影梦境吧！\n该系列商品及上架资讯即将于7月19日揭晓，敬请期待~\n「星稚梦旅」周边表情包现已陆续开放下载，欢迎前往【微信表情包商城】、【抖音表情包商城】以及【米游社】下载使用！\n微信表情包（即将上线）获取Tips：\n1-前往微信“搜一搜”搜索“原神星稚梦旅表情”；\n2-点击导航栏“表情”按钮，进入表情专辑，即可下载使用。\n \n抖音表情包获取Tips：\n1-前往抖音搜索「原神表情包」；\n2-点击「去添加」进入原神表情包界面；\n3-选择相应表情包，点击「添加」即可获得；\n4-获得表情包后，旅行者可在「私信」及「评论界面」使用。\n \n米游社表情包获取Tips：\n1- 前往米游社帖子评论区；\n2- 点击表情中的「派蒙的画作」系列；\n3- 选择相应表情包，即可开始使用。\n\nsource @YuanShen #表情包",
    "content": "《原神》星稚梦旅周边特别企划揭晓 系列表情包现已上线\n\n亲爱的旅行者，《原神》全新「星稚梦旅系列」周边特别企划正式公开，本次与旅行者见面的旅行伙伴有：芙宁娜、达达利亚、菲林斯、钟离、莱欧斯利、哥伦比娅。\n和旅行伙伴一起掠过童年的光影梦境吧！\n该系列商品及上架资讯即将于7月19日揭晓，敬请期待~\n「星稚梦旅」周边表情包现已陆续开放下载，欢迎前往【微信表情包商城】、【抖音表情包商城】以及【米游社】下载使用！\n微信表情包（即将上线）获取Tips：\n1-前往微信“搜一搜”搜索“原神星稚梦旅表情”；\n2-点击导航栏“表情”按钮，进入表情专辑，即可下载使用。\n \n抖音表情包获取Tips：\n1-前往抖音搜索「原神表情包」；\n2-点击「去添加」进入原神表情包界面；\n3-选择相应表情包，点击「添加」即可获得；\n4-获得表情包后，旅行者可在「私信」及「评论界面」使用。\n \n米游社表情包获取Tips：\n1- 前往米游社帖子评论区；\n2- 点击表情中的「派蒙的画作」系列；\n3- 选择相应表情包，即可开始使用。\n\nsource @YuanShen #表情包",
    "image": "https://cora.jackie3137.xyz/f/09df77131d0faabc6c22/Thunder%20File%20To%20Link_20260718100227.jpg",
    "images": [
      "https://cora.jackie3137.xyz/f/09df77131d0faabc6c22/Thunder%20File%20To%20Link_20260718100227.jpg",
      "https://cora.jackie3137.xyz/f/2157182b75883425ab14/Thunder%20File%20To%20Link_20260718100317.jpg",
      "https://cora.jackie3137.xyz/f/7235d574a56fad307033/Thunder%20File%20To%20Link_20260718100408.jpg",
      "https://cora.jackie3137.xyz/f/0b72d14dd0c1c3a672c0/Thunder%20File%20To%20Link_20260718100458.jpg",
      "https://cora.jackie3137.xyz/f/4a501ccf01ac0eedafd5/Thunder%20File%20To%20Link_20260718100548.jpg",
      "https://cora.jackie3137.xyz/f/3720839632ca2f522c21/Thunder%20File%20To%20Link_20260718100638.jpg",
      "https://cora.jackie3137.xyz/f/b66dd302535707e15142/Thunder%20File%20To%20Link_20260718100729.jpg",
      "https://cora.jackie3137.xyz/f/bdf4ab8e4a04583b4ed4/Thunder%20File%20To%20Link_20260718100819.jpg"
    ],
    "videos": [],
    "category": "活动",
    "important": false,
    "pinOrder": 999999,
    "pinExpiry": ""
  },
  {
    "id": 130166,
    "date": "2026-07-18",
    "time": "2026-07-18 10:00:15",
    "channel": "@REVERSE1999CN",
    "title": "#重返未来1999# #重返未来原子之心联动# #重返未来联动# 【鬃毛邮报】即将开启！ 调查传闻中",
    "text": "#重返未来1999# #重返未来原子之心联动# #重返未来联动# 【鬃毛邮报】即将开启！ 调查传闻中的离奇事迹，将线索揣进不漏风的兜里。 我们为最灵通的消息奉上黄金...\n\n#重返未来1999# #重返未来原子之心联动# #重返未来联动# \n【鬃毛邮报】即将开启！\n调查传闻中的离奇事迹，将线索揣进不漏风的兜里。\n我们为最灵通的消息奉上黄金与盛誉。\n\n▶▶活动时间◀◀\n「自我同情者」调查时间：7/23 10:00 - 8/13 4:59\n「信仰的移位·Ⅱ型」调查时间：7/30 5:00 - 8/13 4:59\n「毁灭的履带」调查时间：8/6 5:00 - 8/13 4:59\n\n▶▶开启条件◀◀\n通关主线故事1ST.16「天堂使徒」\n\n▶▶玩法说明◀◀\n※【隐匿度】：根据特殊要求进行削减，削减至0后可进入额外的【目击回合】。削减【隐匿度】还能累计分数，与对首领怪物造成伤害获得的分数一起相加后根据总分评级并记录进【调查进度】中。\n※【目击者等级】：通过在战斗中取得分数来累计经验，提升等级后即可获得奖励。该奖励系统会在后续每次鬃毛邮报开启期间持续累计。\n※【首领图鉴】：收纳了所有首领怪物的信息并可查看“调查建议”。\n\n「自我同情者」薄弱点：星、岩\n「信仰的移位·Ⅱ型」薄弱点：兽、智\n「毁灭的履带 」灵感：星\n\n▶▶主要奖励◀◀\n饕餮、贪欲、共鸣晶匣、悠远的振响、偏振、共鸣材料、洞悉材料     收起 查看大图 向左旋转 向右旋转           \n        重返未来：1999\n       \n          游戏\n         \n          角色扮演/策略/卡牌\n         \n        3.8活动剧情《世纪末尺度》正式上映！注册送超100抽及自选范围六星角色\n       \n        进入\n       \n\n专栏链接：https://www.bilibili.com/opus/1226343732209516547",
    "content": "#重返未来1999# #重返未来原子之心联动# #重返未来联动# 【鬃毛邮报】即将开启！ 调查传闻中的离奇事迹，将线索揣进不漏风的兜里。 我们为最灵通的消息奉上黄金...\n\n#重返未来1999# #重返未来原子之心联动# #重返未来联动# \n【鬃毛邮报】即将开启！\n调查传闻中的离奇事迹，将线索揣进不漏风的兜里。\n我们为最灵通的消息奉上黄金与盛誉。\n\n▶▶活动时间◀◀\n「自我同情者」调查时间：7/23 10:00 - 8/13 4:59\n「信仰的移位·Ⅱ型」调查时间：7/30 5:00 - 8/13 4:59\n「毁灭的履带」调查时间：8/6 5:00 - 8/13 4:59\n\n▶▶开启条件◀◀\n通关主线故事1ST.16「天堂使徒」\n\n▶▶玩法说明◀◀\n※【隐匿度】：根据特殊要求进行削减，削减至0后可进入额外的【目击回合】。削减【隐匿度】还能累计分数，与对首领怪物造成伤害获得的分数一起相加后根据总分评级并记录进【调查进度】中。\n※【目击者等级】：通过在战斗中取得分数来累计经验，提升等级后即可获得奖励。该奖励系统会在后续每次鬃毛邮报开启期间持续累计。\n※【首领图鉴】：收纳了所有首领怪物的信息并可查看“调查建议”。\n\n「自我同情者」薄弱点：星、岩\n「信仰的移位·Ⅱ型」薄弱点：兽、智\n「毁灭的履带 」灵感：星\n\n▶▶主要奖励◀◀\n饕餮、贪欲、共鸣晶匣、悠远的振响、偏振、共鸣材料、洞悉材料     收起 查看大图 向左旋转 向右旋转           \n        重返未来：1999\n       \n          游戏\n         \n          角色扮演/策略/卡牌\n         \n        3.8活动剧情《世纪末尺度》正式上映！注册送超100抽及自选范围六星角色\n       \n        进入\n       \n\n专栏链接：https://www.bilibili.com/opus/1226343732209516547",
    "image": "https://cora.jackie3137.xyz/f/f3682a5dbd49884a0cce/Thunder%20File%20To%20Link_20260718100027.jpg",
    "images": [
      "https://cora.jackie3137.xyz/f/f3682a5dbd49884a0cce/Thunder%20File%20To%20Link_20260718100027.jpg",
      "https://cora.jackie3137.xyz/f/1a147786d9ce35ae8c35/Thunder%20File%20To%20Link_20260717100229.jpg"
    ],
    "videos": [],
    "category": "活动",
    "important": false,
    "pinOrder": 999999,
    "pinExpiry": ""
  },
  {
    "id": 852,
    "date": "2026-07-18",
    "time": "2026-07-18 09:03:12",
    "channel": "@ARKTIPS",
    "title": "2026.7.18\n制作组通讯#67期\n\n感谢大家一直以来对《明日方舟》的关注与支持，很高兴和大家再",
    "text": "2026.7.18\n制作组通讯#67期\n\n感谢大家一直以来对《明日方舟》的关注与支持，很高兴和大家再次见面。在本期制作组通讯发布之际，集成战略【沉沦者的黑流树海】已经开启，欢迎大家体验，同时也再次感谢大家对于此前「丛林症结」故事集活动的喜爱与支持。\n\n以下，则是本次制作组通讯为大家带来的最新一期的相关活动及版本内容：\n\n【通讯节点·一】\n◆《明日方舟》2026夏日嘉年华特别通讯将于07月25日19:30进行。\n◆ 观看地址：https://live.bilibili.com/5555734\n◆本次特别通讯将主要介绍《明日方舟》2026夏日嘉年华系列活动、全新SideStory、新一期【限定寻访】、后续版本计划等内容，届时欢迎大家前来观看。\n\n●更多夏日嘉年华相关活动内容可关注2026夏日嘉年华特别通讯。\n\n最后，感谢大家阅读本期制作组通讯，以下为本次的制作组通讯奖励：\n\n奖励内容：合成玉*200、类凝结核*5\n发放时间：07月18日17:00（邮件领取有效期：7日）\n发放范围：07月18日17:00前所有注册并创建角色的玩家\n\n*制作组通讯并不代表版本更新及活动最终内容，详细活动计划与版本更新内容等请以届时相关公告为准*\n\n《明日方舟》制作组\n2026年07月18日",
    "content": "2026.7.18\n制作组通讯#67期\n\n感谢大家一直以来对《明日方舟》的关注与支持，很高兴和大家再次见面。在本期制作组通讯发布之际，集成战略【沉沦者的黑流树海】已经开启，欢迎大家体验，同时也再次感谢大家对于此前「丛林症结」故事集活动的喜爱与支持。\n\n以下，则是本次制作组通讯为大家带来的最新一期的相关活动及版本内容：\n\n【通讯节点·一】\n◆《明日方舟》2026夏日嘉年华特别通讯将于07月25日19:30进行。\n◆ 观看地址：https://live.bilibili.com/5555734\n◆本次特别通讯将主要介绍《明日方舟》2026夏日嘉年华系列活动、全新SideStory、新一期【限定寻访】、后续版本计划等内容，届时欢迎大家前来观看。\n\n●更多夏日嘉年华相关活动内容可关注2026夏日嘉年华特别通讯。\n\n最后，感谢大家阅读本期制作组通讯，以下为本次的制作组通讯奖励：\n\n奖励内容：合成玉*200、类凝结核*5\n发放时间：07月18日17:00（邮件领取有效期：7日）\n发放范围：07月18日17:00前所有注册并创建角色的玩家\n\n*制作组通讯并不代表版本更新及活动最终内容，详细活动计划与版本更新内容等请以届时相关公告为准*\n\n《明日方舟》制作组\n2026年07月18日",
    "image": "https://cora.jackie3137.xyz/f/404ccbd8f3ab4b6f0e04/Thunder%20File%20To%20Link_20260718090313.jpg",
    "images": [
      "https://cora.jackie3137.xyz/f/404ccbd8f3ab4b6f0e04/Thunder%20File%20To%20Link_20260718090313.jpg"
    ],
    "videos": [],
    "category": "活动",
    "important": false,
    "pinOrder": 999999,
    "pinExpiry": ""
  },
  {
    "id": 1312,
    "date": "2026-07-18",
    "time": "2026-07-18 09:00:56",
    "channel": "@ARKBULLETIN_CN",
    "title": "新游戏内公告：https://telegra.ph/制作组通讯67期-07-18\n省流：公告感谢玩家",
    "text": "制作组通讯#67期\n感谢大家一直以来对《明日方舟》的关注与支持，很高兴和大家再次见面。在本期制作组通讯发布之际，集成战略【沉沦者的黑流树海】已经开启，欢迎大家体验，同时也再次感谢大家对于此前「丛林症结」故事集活动的喜爱与支持。\n以下，则是本次制作组通讯为大家带来的最新一期的相关活动及版本内容：\n【通讯节点·一】\n◆《明日方舟》2026夏日嘉年华特别通讯将于07月25日19:30进行。\n◆ 观看地址：\nhttps://live.bilibili.com/5555734\n、\nhttps://v.douyin.com/iLRYEJTV/\n、\nhttps://weibo.com/arknights\n或\nhttps://live.kuaishou.com/u/3xqny5i9rzzy96e\n◆本次特别通讯将主要介绍《明日方舟》2026夏日嘉年华系列活动、全新SideStory、新一期【限定寻访】、后续版本计划等内容，届时欢迎大家前来观看。\n●更多夏日嘉年华相关活动内容可关注2026夏日嘉年华特别通讯。\n最后，感谢大家阅读本期制作组通讯，以下为本次的制作组通讯奖励：\n奖励内容：\n合成玉*200、类凝结核*5\n发放时间：\n07月18日17:00（邮件领取有效期：7日）\n发放范围：\n07月18日17:00前所有注册并创建角色的玩家\n*制作组通讯并不代表版本更新及活动最终内容，详细活动计划与版本更新内容等请以届时相关公告为准*\n《明日方舟》制作组\n2026年07月18日",
    "content": "制作组通讯#67期\n感谢大家一直以来对《明日方舟》的关注与支持，很高兴和大家再次见面。在本期制作组通讯发布之际，集成战略【沉沦者的黑流树海】已经开启，欢迎大家体验，同时也再次感谢大家对于此前「丛林症结」故事集活动的喜爱与支持。\n以下，则是本次制作组通讯为大家带来的最新一期的相关活动及版本内容：\n【通讯节点·一】\n◆《明日方舟》2026夏日嘉年华特别通讯将于07月25日19:30进行。\n◆ 观看地址：\nhttps://live.bilibili.com/5555734\n、\nhttps://v.douyin.com/iLRYEJTV/\n、\nhttps://weibo.com/arknights\n或\nhttps://live.kuaishou.com/u/3xqny5i9rzzy96e\n◆本次特别通讯将主要介绍《明日方舟》2026夏日嘉年华系列活动、全新SideStory、新一期【限定寻访】、后续版本计划等内容，届时欢迎大家前来观看。\n●更多夏日嘉年华相关活动内容可关注2026夏日嘉年华特别通讯。\n最后，感谢大家阅读本期制作组通讯，以下为本次的制作组通讯奖励：\n奖励内容：\n合成玉*200、类凝结核*5\n发放时间：\n07月18日17:00（邮件领取有效期：7日）\n发放范围：\n07月18日17:00前所有注册并创建角色的玩家\n*制作组通讯并不代表版本更新及活动最终内容，详细活动计划与版本更新内容等请以届时相关公告为准*\n《明日方舟》制作组\n2026年07月18日",
    "image": "https://cora.jackie3137.xyz/f/085a223df6b8298aa846/Thunder%20File%20To%20Link_20260718090101.jpg",
    "images": [
      "https://cora.jackie3137.xyz/f/085a223df6b8298aa846/Thunder%20File%20To%20Link_20260718090101.jpg"
    ],
    "videos": [],
    "category": "活动",
    "important": false,
    "pinOrder": 999999,
    "pinExpiry": ""
  },
  {
    "id": 851,
    "date": "2026-07-18",
    "time": "2026-07-18 09:01:44",
    "channel": "@ARKTIPS",
    "title": "https://www.bilibilibb.com/video/BV1VqKF6zEJa/",
    "text": "https://www.bilibilibb.com/video/BV1VqKF6zEJa/",
    "content": "https://www.bilibilibb.com/video/BV1VqKF6zEJa/",
    "image": "",
    "images": [],
    "videos": [],
    "category": "活动",
    "important": false,
    "pinOrder": 999999,
    "pinExpiry": ""
  },
  {
    "id": 90,
    "date": "2026-07-18",
    "time": "2026-07-18 06:00:14",
    "channel": "@ENDFIELDBULLETINGPT",
    "title": "新游戏内公告：森空岛向渊行创作者激励活动\n#资讯速报",
    "text": "新游戏内公告：森空岛向渊行创作者激励活动\n#资讯速报",
    "content": "新游戏内公告：森空岛向渊行创作者激励活动\n#资讯速报",
    "image": "https://cora.jackie3137.xyz/f/6ae37864cdd23f395c5b/Thunder%20File%20To%20Link_20260718060015.jpg",
    "images": [
      "https://cora.jackie3137.xyz/f/6ae37864cdd23f395c5b/Thunder%20File%20To%20Link_20260718060015.jpg"
    ],
    "videos": [],
    "category": "活动",
    "important": false,
    "pinOrder": 999999,
    "pinExpiry": ""
  },
  {
    "id": 6698,
    "date": "2026-07-18",
    "time": "2026-07-18 04:04:12",
    "channel": "@YUANSHEN",
    "title": "「新月终临」——哥伦比娅·小记\n\n旅行者好呀！\n「她捧起月光向人间倾洒，曾经迷途的白鸽，终于找到了归",
    "text": "「新月终临」——哥伦比娅·小记\n\n旅行者好呀！\n「她捧起月光向人间倾洒，曾经迷途的白鸽，终于找到了归乡的道路...」\n「伴月同眠」祈愿将于2026/07/21 18:00开启，届时「空月归乡·哥伦比娅(水)」的祈愿获取概率将大幅提升！\n点击了解更多「月之八」版本内容：\n>>原神「『空月之歌·谐谑』映夏！归乡？千灵节！」内容专题页<<\n\nsource @YuanShen #角色小记",
    "content": "「新月终临」——哥伦比娅·小记\n\n旅行者好呀！\n「她捧起月光向人间倾洒，曾经迷途的白鸽，终于找到了归乡的道路...」\n「伴月同眠」祈愿将于2026/07/21 18:00开启，届时「空月归乡·哥伦比娅(水)」的祈愿获取概率将大幅提升！\n点击了解更多「月之八」版本内容：\n>>原神「『空月之歌·谐谑』映夏！归乡？千灵节！」内容专题页<<\n\nsource @YuanShen #角色小记",
    "image": "https://cora.jackie3137.xyz/f/2792c19ca56c4c56bb99/Thunder%20File%20To%20Link_20260718040535.jpg",
    "images": [
      "https://cora.jackie3137.xyz/f/2792c19ca56c4c56bb99/Thunder%20File%20To%20Link_20260718040535.jpg",
      "https://cora.jackie3137.xyz/f/5a4a6322f235f396c4c6/Thunder%20File%20To%20Link_20260718040805.jpg",
      "https://cora.jackie3137.xyz/f/899d37b885ac9a0855ab/Thunder%20File%20To%20Link_20260718041036.jpg",
      "https://cora.jackie3137.xyz/f/cb390428fad48abf70e6/Thunder%20File%20To%20Link_20260718041307.jpg",
      "https://cora.jackie3137.xyz/f/ab915bce71b5840342cd/Thunder%20File%20To%20Link_20260718041537.jpg",
      "https://cora.jackie3137.xyz/f/29c614601430f1b0d292/Thunder%20File%20To%20Link_20260718041818.jpg",
      "https://cora.jackie3137.xyz/f/33afa9b808ef28ac1c8f/Thunder%20File%20To%20Link_20260718041959.jpg"
    ],
    "videos": [],
    "category": "活动",
    "important": false,
    "pinOrder": 999999,
    "pinExpiry": ""
  },
  {
    "id": 130154,
    "date": "2026-07-18",
    "time": "2026-07-18 04:01:03",
    "channel": "@REVERSE1999CN",
    "title": "重返未来1999\n\n#重返未来1999# #重返未来原子之心联动# #重返未来联动# \n//衣着上新",
    "text": "重返未来1999\n\n#重返未来1999# #重返未来原子之心联动# #重返未来联动# \n//衣着上新\n称量罪与理 | Weighing Sin and Justice\n*二十一又一*系列，玛丽安娜全新衣着。\n焚毁罪孽而冶炼公理。\n\n▶▶衣着宣传折页◀◀\n※全新神秘术特效\n※全新箱中姿态\n※“尤提姆”新装\n※全新释放神秘术语音、音效\n※全新Live2D交互动作×2\n※全新战斗入场效果\n※全新荒原动作\n※崭新形象\n※崭新单品×3 \n\n▶▶获取途径◀◀\n7/23 10:00 - 8/13 4:59，玛丽安娜新增衣着「称量罪与理」将在【衣着风尚】商店上架并限时售卖。\n\n\n图文地址：https://www.bilibili.com/opus/1226250960893902867",
    "content": "重返未来1999\n\n#重返未来1999# #重返未来原子之心联动# #重返未来联动# \n//衣着上新\n称量罪与理 | Weighing Sin and Justice\n*二十一又一*系列，玛丽安娜全新衣着。\n焚毁罪孽而冶炼公理。\n\n▶▶衣着宣传折页◀◀\n※全新神秘术特效\n※全新箱中姿态\n※“尤提姆”新装\n※全新释放神秘术语音、音效\n※全新Live2D交互动作×2\n※全新战斗入场效果\n※全新荒原动作\n※崭新形象\n※崭新单品×3 \n\n▶▶获取途径◀◀\n7/23 10:00 - 8/13 4:59，玛丽安娜新增衣着「称量罪与理」将在【衣着风尚】商店上架并限时售卖。\n\n\n图文地址：https://www.bilibili.com/opus/1226250960893902867",
    "image": "https://cora.jackie3137.xyz/f/3172a4adba71f63adab4/Thunder%20File%20To%20Link_20260718040124.jpg",
    "images": [
      "https://cora.jackie3137.xyz/f/3172a4adba71f63adab4/Thunder%20File%20To%20Link_20260718040124.jpg",
      "https://cora.jackie3137.xyz/f/f7fabd5d9c525103b459/Thunder%20File%20To%20Link_20260718040214.jpg",
      "https://cora.jackie3137.xyz/f/45974357ddde99439fd7/Thunder%20File%20To%20Link_20260718040304.jpg",
      "https://cora.jackie3137.xyz/f/a0dce72158cea30051c6/Thunder%20File%20To%20Link_20260718040444.jpg",
      "https://cora.jackie3137.xyz/f/408729093aaf15d5dcce/Thunder%20File%20To%20Link_20260718040715.jpg",
      "https://cora.jackie3137.xyz/f/f5af57894b3e0bcaa9a8/Thunder%20File%20To%20Link_20260718040946.jpg",
      "https://cora.jackie3137.xyz/f/c6d93b4356568131ad8e/Thunder%20File%20To%20Link_20260718041216.jpg",
      "https://cora.jackie3137.xyz/f/be0b19a456a94ccff572/Thunder%20File%20To%20Link_20260718041447.jpg",
      "https://cora.jackie3137.xyz/f/33aa2a0f993e9a983ff9/Thunder%20File%20To%20Link_20260718041718.jpg"
    ],
    "videos": [],
    "category": "活动",
    "important": false,
    "pinOrder": 999999,
    "pinExpiry": ""
  },
  {
    "id": 8043,
    "date": "2026-07-17",
    "time": "2026-07-17 16:30:14",
    "channel": "@MCKURO",
    "title": "《RUNNING FOR YOUR LIFE（无所遁藏）》 | 《鸣潮》演唱会\n\n“沸腾的本能在嘶吼",
    "text": "《RUNNING FOR YOUR LIFE（无所遁藏）》 | 《鸣潮》演唱会\n\n“沸腾的本能在嘶吼，告诉我你为何而战。”\n\n《鸣潮》巡回演唱会「致予新世界」线上直播将于2026年7月18日19:05正式播出。\n\nsource @MCKURO",
    "content": "《RUNNING FOR YOUR LIFE（无所遁藏）》 | 《鸣潮》演唱会\n\n“沸腾的本能在嘶吼，告诉我你为何而战。”\n\n《鸣潮》巡回演唱会「致予新世界」线上直播将于2026年7月18日19:05正式播出。\n\nsource @MCKURO",
    "image": "https://cora.jackie3137.xyz/f/b51d59a2820f6752edb0/Thunder%20File%20To%20Link_20260717163018.jpg",
    "images": [
      "https://cora.jackie3137.xyz/f/b51d59a2820f6752edb0/Thunder%20File%20To%20Link_20260717163018.jpg"
    ],
    "videos": [],
    "category": "活动",
    "important": false,
    "pinOrder": 999999,
    "pinExpiry": ""
  },
  {
    "id": 850,
    "date": "2026-07-17",
    "time": "2026-07-17 11:11:42",
    "channel": "@ARKTIPS",
    "title": "26.7.17\n黒柳书海肉鸽\n本源研修分队相关",
    "text": "26.7.17\n黒柳书海肉鸽\n本源研修分队相关",
    "content": "26.7.17\n黒柳书海肉鸽\n本源研修分队相关",
    "image": "https://cora.jackie3137.xyz/f/bcfeeb61206001a40949/Thunder%20File%20To%20Link_20260717111142.jpg",
    "images": [
      "https://cora.jackie3137.xyz/f/bcfeeb61206001a40949/Thunder%20File%20To%20Link_20260717111142.jpg"
    ],
    "videos": [],
    "category": "活动",
    "important": false,
    "pinOrder": 999999,
    "pinExpiry": ""
  },
  {
    "id": 130140,
    "date": "2026-07-17",
    "time": "2026-07-17 10:00:26",
    "channel": "@REVERSE1999CN",
    "title": "#重返未来1999# #重返未来原子之心联动# #重返未来联动# 周期挑战玩法【焦点闪回】即将开启！",
    "text": "#重返未来1999# #重返未来原子之心联动# #重返未来联动# 周期挑战玩法【焦点闪回】即将开启！ 情绪自深渊中泛滥，预谋劫持一束希望。 ▶▶活动时间◀◀ 7/23 10:...\n\n#重返未来1999# #重返未来原子之心联动# #重返未来联动# \n周期挑战玩法【焦点闪回】即将开启！\n情绪自深渊中泛滥，预谋劫持一束希望。\n\n▶▶活动时间◀◀\n7/23 10:00 - 8/13 4:59\n\n▶▶开启条件◀◀\n通关主线故事3RD.02「青蛙与太妃」\n\n▶▶玩法说明◀◀\n活动期间，使用多支队伍挑战关卡，在特定数量的回合内完成挑战获取星级，累计星级即可获取奖励\n\n▶▶主要奖励◀◀\n「神思母本」、独一律·【湖的涟漪】、恢奇帜     收起 查看大图 向左旋转 向右旋转           \n        重返未来：1999\n       \n          游戏\n         \n          角色扮演/策略/卡牌\n         \n        3.8活动剧情《世纪末尺度》正式上映！注册送超100抽及自选范围六星角色\n       \n        进入\n       \n\n专栏链接：https://www.bilibili.com/opus/1225972646989004803",
    "content": "#重返未来1999# #重返未来原子之心联动# #重返未来联动# 周期挑战玩法【焦点闪回】即将开启！ 情绪自深渊中泛滥，预谋劫持一束希望。 ▶▶活动时间◀◀ 7/23 10:...\n\n#重返未来1999# #重返未来原子之心联动# #重返未来联动# \n周期挑战玩法【焦点闪回】即将开启！\n情绪自深渊中泛滥，预谋劫持一束希望。\n\n▶▶活动时间◀◀\n7/23 10:00 - 8/13 4:59\n\n▶▶开启条件◀◀\n通关主线故事3RD.02「青蛙与太妃」\n\n▶▶玩法说明◀◀\n活动期间，使用多支队伍挑战关卡，在特定数量的回合内完成挑战获取星级，累计星级即可获取奖励\n\n▶▶主要奖励◀◀\n「神思母本」、独一律·【湖的涟漪】、恢奇帜     收起 查看大图 向左旋转 向右旋转           \n        重返未来：1999\n       \n          游戏\n         \n          角色扮演/策略/卡牌\n         \n        3.8活动剧情《世纪末尺度》正式上映！注册送超100抽及自选范围六星角色\n       \n        进入\n       \n\n专栏链接：https://www.bilibili.com/opus/1225972646989004803",
    "image": "https://cora.jackie3137.xyz/f/39d76376835a59faa0e7/Thunder%20File%20To%20Link_20260717100038.jpg",
    "images": [
      "https://cora.jackie3137.xyz/f/39d76376835a59faa0e7/Thunder%20File%20To%20Link_20260717100038.jpg",
      "https://cora.jackie3137.xyz/f/1a147786d9ce35ae8c35/Thunder%20File%20To%20Link_20260717100229.jpg"
    ],
    "videos": [],
    "category": "活动",
    "important": false,
    "pinOrder": 999999,
    "pinExpiry": ""
  },
  {
    "id": 130141,
    "date": "2026-07-17",
    "time": "2026-07-17 10:00:43",
    "channel": "@REVERSE1999CN",
    "title": "重返未来1999\n\n#重返未来1999# #重返未来原子之心联动# #重返未来联动# \n周期挑战玩法",
    "text": "重返未来1999\n\n#重返未来1999# #重返未来原子之心联动# #重返未来联动# \n周期挑战玩法【焦点闪回】即将开启！\n情绪自深渊中泛滥，预谋劫持一束希望。\n\n▶▶活动时间◀◀\n7/23 10:00 - 8/13 4:59\n\n▶▶开启条件◀◀\n通关主线故事3RD.02「青蛙与太妃」\n\n▶▶玩法说明◀◀\n活动期间，使用多支队伍挑战关卡，在特定数量的回合内完成挑战获取星级，累计星级即可获取奖励\n\n▶▶主要奖励◀◀\n「神思母本」、独一律·【湖的涟漪】、恢奇帜\n\n\n图文地址：https://www.bilibili.com/opus/1225972646989004803",
    "content": "重返未来1999\n\n#重返未来1999# #重返未来原子之心联动# #重返未来联动# \n周期挑战玩法【焦点闪回】即将开启！\n情绪自深渊中泛滥，预谋劫持一束希望。\n\n▶▶活动时间◀◀\n7/23 10:00 - 8/13 4:59\n\n▶▶开启条件◀◀\n通关主线故事3RD.02「青蛙与太妃」\n\n▶▶玩法说明◀◀\n活动期间，使用多支队伍挑战关卡，在特定数量的回合内完成挑战获取星级，累计星级即可获取奖励\n\n▶▶主要奖励◀◀\n「神思母本」、独一律·【湖的涟漪】、恢奇帜\n\n\n图文地址：https://www.bilibili.com/opus/1225972646989004803",
    "image": "https://cora.jackie3137.xyz/f/0bac199643b61dfec883/Thunder%20File%20To%20Link_20260717100130.jpg",
    "images": [
      "https://cora.jackie3137.xyz/f/0bac199643b61dfec883/Thunder%20File%20To%20Link_20260717100130.jpg"
    ],
    "videos": [],
    "category": "活动",
    "important": false,
    "pinOrder": 999999,
    "pinExpiry": ""
  },
  {
    "id": 849,
    "date": "2026-07-17",
    "time": "2026-07-17 09:57:11",
    "channel": "@ARKTIPS",
    "title": "干员-作业匹配工具：\n\nhttps://ark.yituliu.cn/tools/operator-",
    "text": "干员-作业匹配工具：\n\nhttps://ark.yituliu.cn/tools/operator-zoot-matcher",
    "content": "干员-作业匹配工具：\n\nhttps://ark.yituliu.cn/tools/operator-zoot-matcher",
    "image": "",
    "images": [],
    "videos": [],
    "category": "活动",
    "important": false,
    "pinOrder": 999999,
    "pinExpiry": ""
  },
  {
    "id": 130138,
    "date": "2026-07-17",
    "time": "2026-07-17 09:07:36",
    "channel": "@REVERSE1999CN",
    "title": "#重返未来1999音乐会# #众声漫游夜# #重返未来1999抽门票##重返未来1999# 《重返未",
    "text": "#重返未来1999音乐会# #众声漫游夜# #重返未来1999抽门票##重返未来1999# 《重返未来：1999》音乐会「众声漫游夜」主题活动正式上线，有机会获得音乐会门票，欢...\n\n#重返未来1999音乐会# #众声漫游夜# #重返未来1999抽门票##重返未来1999# \n《重返未来：1999》音乐会「众声漫游夜」主题活动正式上线，有机会获得音乐会门票，欢迎司辰前往参与活动。\n\n▶▶活动时间◀◀\n2026/7/17 17:00 - 8/2 23:59\n活动入口：【打开QQ音乐/ 酷狗音乐App】→【搜索“重返未来1999”】\n\n▶▶活动奖励◀◀\n※完成关注任务获得：纯雨滴*30\n※完成升级勋章有机会获得：音乐会门票、游戏周边、音乐会限定魔精勋章\n※完成抽奖任务有机会获得：音乐会门票、纯雨滴、养成材料\n※完成优质评论征集活动有机会获得：音乐会门票、游戏周边\n\n▶▶转发抽奖◀◀互动抽奖 \n关注@重返未来1999 并转发本条动态，我们将于2026年8月2日抽取3名玩家送出【随机官方周边*1】！\n\n▶▶活动说明◀◀\n1. 活动期间，完成活动页内关注任务，即可获得纯雨滴*30，获得兑换码后，可前往游戏内「设置」-「账户」-「兑换码」领取礼包。\n\n2. 活动期间，完成活动页内升级勋章任务，必得音乐会限定魔精勋章，在QQ音乐平台有机会抽取「众声漫游夜」音乐会门票，在酷狗音乐平台有机会抽取精美周边。\n本模块中奖者会收到系统弹窗提示，请注意填写信息。此外也可点击QQ音乐APP「我的」-「会员中心」-「我的资产」-「优惠券」进行查看和填写。\n\n3.活动期间，完成活动页内抽奖任务，在QQ音乐平台有机会抽取「众声漫游夜」音乐会门票，两平台均有机会抽取纯雨滴与养成材料。\n本模块门票中奖者会收到系统弹窗提示，请注意填写信息。此外也可点击QQ音乐APP「我的」-「会员中心」-「我的资产」-「优惠券」进行查看和填写。游戏资源以兑换码形式发放，可前往游戏内「设置」-「账户「-「兑换码」领取礼包。\n\n4. 活动期间，参与优质评论征集活动，被选中的优质乐评有机会登上「优质乐评」区域，在QQ音乐平台有机会获得「众声漫游夜」音乐会门票，在酷狗音乐平台有机会抽取精美周边。\n本模块中奖者将会收到音乐平台官方账号的私信，请注意査收。\n\n更多音乐活动请查看活动页面。\n\n▶▶温馨提示◀◀\n1.每个游戏ID仅可领取1次养成材料礼包、纯雨滴*30。（若QQ音乐与酷狗音乐重复获取兑换码，也仅可兑换1次）；\n2.每位用户每个抽奖任务仅限参与1次，在活动期间完成全部任务最多可获4次抽奖机会。（若QQ音乐与酷狗音乐重复抽取，也仅可兑换4次）；\n3.活动兑换码有效期截止至2026年8月15日23:59，请在有效期内进行兑换。\n4.抽奖活动道具数量有限，发完即止。\n*具体活动规则，请查看活动页面内“活动规则”。\n            长图\n               收起 查看大图 向左旋转 向右旋转           \n        重返未来：1999\n       \n          游戏\n         \n          角色扮演/策略/卡牌\n         \n        3.8活动剧情《世纪末尺度》正式上映！注册送超100抽及自选范围六星角色\n       \n        进入\n       \n\n专栏链接：https://www.bilibili.com/opus/1225957238824239160",
    "content": "#重返未来1999音乐会# #众声漫游夜# #重返未来1999抽门票##重返未来1999# 《重返未来：1999》音乐会「众声漫游夜」主题活动正式上线，有机会获得音乐会门票，欢...\n\n#重返未来1999音乐会# #众声漫游夜# #重返未来1999抽门票##重返未来1999# \n《重返未来：1999》音乐会「众声漫游夜」主题活动正式上线，有机会获得音乐会门票，欢迎司辰前往参与活动。\n\n▶▶活动时间◀◀\n2026/7/17 17:00 - 8/2 23:59\n活动入口：【打开QQ音乐/ 酷狗音乐App】→【搜索“重返未来1999”】\n\n▶▶活动奖励◀◀\n※完成关注任务获得：纯雨滴*30\n※完成升级勋章有机会获得：音乐会门票、游戏周边、音乐会限定魔精勋章\n※完成抽奖任务有机会获得：音乐会门票、纯雨滴、养成材料\n※完成优质评论征集活动有机会获得：音乐会门票、游戏周边\n\n▶▶转发抽奖◀◀互动抽奖 \n关注@重返未来1999 并转发本条动态，我们将于2026年8月2日抽取3名玩家送出【随机官方周边*1】！\n\n▶▶活动说明◀◀\n1. 活动期间，完成活动页内关注任务，即可获得纯雨滴*30，获得兑换码后，可前往游戏内「设置」-「账户」-「兑换码」领取礼包。\n\n2. 活动期间，完成活动页内升级勋章任务，必得音乐会限定魔精勋章，在QQ音乐平台有机会抽取「众声漫游夜」音乐会门票，在酷狗音乐平台有机会抽取精美周边。\n本模块中奖者会收到系统弹窗提示，请注意填写信息。此外也可点击QQ音乐APP「我的」-「会员中心」-「我的资产」-「优惠券」进行查看和填写。\n\n3.活动期间，完成活动页内抽奖任务，在QQ音乐平台有机会抽取「众声漫游夜」音乐会门票，两平台均有机会抽取纯雨滴与养成材料。\n本模块门票中奖者会收到系统弹窗提示，请注意填写信息。此外也可点击QQ音乐APP「我的」-「会员中心」-「我的资产」-「优惠券」进行查看和填写。游戏资源以兑换码形式发放，可前往游戏内「设置」-「账户「-「兑换码」领取礼包。\n\n4. 活动期间，参与优质评论征集活动，被选中的优质乐评有机会登上「优质乐评」区域，在QQ音乐平台有机会获得「众声漫游夜」音乐会门票，在酷狗音乐平台有机会抽取精美周边。\n本模块中奖者将会收到音乐平台官方账号的私信，请注意査收。\n\n更多音乐活动请查看活动页面。\n\n▶▶温馨提示◀◀\n1.每个游戏ID仅可领取1次养成材料礼包、纯雨滴*30。（若QQ音乐与酷狗音乐重复获取兑换码，也仅可兑换1次）；\n2.每位用户每个抽奖任务仅限参与1次，在活动期间完成全部任务最多可获4次抽奖机会。（若QQ音乐与酷狗音乐重复抽取，也仅可兑换4次）；\n3.活动兑换码有效期截止至2026年8月15日23:59，请在有效期内进行兑换。\n4.抽奖活动道具数量有限，发完即止。\n*具体活动规则，请查看活动页面内“活动规则”。\n            长图\n               收起 查看大图 向左旋转 向右旋转           \n        重返未来：1999\n       \n          游戏\n         \n          角色扮演/策略/卡牌\n         \n        3.8活动剧情《世纪末尺度》正式上映！注册送超100抽及自选范围六星角色\n       \n        进入\n       \n\n专栏链接：https://www.bilibili.com/opus/1225957238824239160",
    "image": "",
    "images": [],
    "videos": [],
    "category": "活动",
    "important": false,
    "pinOrder": 999999,
    "pinExpiry": ""
  },
  {
    "id": 130137,
    "date": "2026-07-17",
    "time": "2026-07-17 09:06:29",
    "channel": "@REVERSE1999CN",
    "title": "重返未来1999\n\n#重返未来1999音乐会# #众声漫游夜# #重返未来1999抽门票##重返未来",
    "text": "重返未来1999\n\n#重返未来1999音乐会# #众声漫游夜# #重返未来1999抽门票##重返未来1999# \n《重返未来：1999》音乐会「众声漫游夜」主题活动正式上线，有机会获得音乐会门票，欢迎司辰前往参与活动。\n\n▶▶活动时间◀◀\n2026/7/17 17:00 - 8/2 23:59\n活动入口：【打开QQ音乐/ 酷狗音乐App】→【搜索“重返未来1999”】\n\n▶▶活动奖励◀◀\n※完成关注任务获得：纯雨滴*30\n※完成升级勋章有机会获得：音乐会门票、游戏周边、音乐会限定魔精勋章\n※完成抽奖任务有机会获得：音乐会门票、纯雨滴、养成材料\n※完成优质评论征集活动有机会获得：音乐会门票、游戏周边\n\n▶▶转发抽奖◀◀互动抽奖 \n关注@重返未来1999 并转发本条动态，我们将于2026年8月2日抽取3名玩家送出【随机官方周边*1】！\n\n▶▶活动说明◀◀\n1. 活动期间，完成活动页内关注任务，即可获得纯雨滴*30，获得兑换码后，可前往游戏内「设置」-「账户」-「兑换码」领取礼包。\n\n2. 活动期间，完成活动页内升级勋章任务，必得音乐会限定魔精勋章，在QQ音乐平台有机会抽取「众声漫游夜」音乐会门票，在酷狗音乐平台有机会抽取精美周边。\n本模块中奖者会收到系统弹窗提示，请注意填写信息。此外也可点击QQ音乐APP「我的」-「会员中心」-「我的资产」-「优惠券」进行查看和填写。\n\n3.活动期间，完成活动页内抽奖任务，在QQ音乐平台有机会抽取「众声漫游夜」音乐会门票，两平台均有机会抽取纯雨滴与养成材料。\n本模块门票中奖者会收到系统弹窗提示，请注意填写信息。此外也可点击QQ音乐APP「我的」-「会员中心」-「我的资产」-「优惠券」进行查看和填写。游戏资源以兑换码形式发放，可前往游戏内「设置」-「账户「-「兑换码」领取礼包。\n\n4. 活动期间，参与优质评论征集活动，被选中的优质乐评有机会登上「优质乐评」区域，在QQ音乐平台有机会获得「众声漫游夜」音乐会门票，在酷狗音乐平台有机会抽取精美周边。\n本模块中奖者将会收到音乐平台官方账号的私信，请注意査收。\n\n更多音乐活动请查看活动页面。\n\n▶▶温馨提示◀◀\n1.每个游戏ID仅可领取1次养成材料礼包、纯雨滴*30。（若QQ音乐与酷狗音乐重复获取兑换码，也仅可兑换1次）；\n2.每位用户每个抽奖任务仅限参与1次，在活动期间完成全部任务最多可获4次抽奖机会。（若QQ音乐与酷狗音乐重复抽取，也仅可兑换4次）；\n3.活动兑换码有效期截止至2026年8月15日23:59，请在有效期内进行兑换。\n4.抽奖活动道具数量有限，发完即止。\n*具体活动规则，请查看活动页面内“活动规则”。\n\n\n图文地址：https://www.bilibili.com/opus/1225957238824239160",
    "content": "重返未来1999\n\n#重返未来1999音乐会# #众声漫游夜# #重返未来1999抽门票##重返未来1999# \n《重返未来：1999》音乐会「众声漫游夜」主题活动正式上线，有机会获得音乐会门票，欢迎司辰前往参与活动。\n\n▶▶活动时间◀◀\n2026/7/17 17:00 - 8/2 23:59\n活动入口：【打开QQ音乐/ 酷狗音乐App】→【搜索“重返未来1999”】\n\n▶▶活动奖励◀◀\n※完成关注任务获得：纯雨滴*30\n※完成升级勋章有机会获得：音乐会门票、游戏周边、音乐会限定魔精勋章\n※完成抽奖任务有机会获得：音乐会门票、纯雨滴、养成材料\n※完成优质评论征集活动有机会获得：音乐会门票、游戏周边\n\n▶▶转发抽奖◀◀互动抽奖 \n关注@重返未来1999 并转发本条动态，我们将于2026年8月2日抽取3名玩家送出【随机官方周边*1】！\n\n▶▶活动说明◀◀\n1. 活动期间，完成活动页内关注任务，即可获得纯雨滴*30，获得兑换码后，可前往游戏内「设置」-「账户」-「兑换码」领取礼包。\n\n2. 活动期间，完成活动页内升级勋章任务，必得音乐会限定魔精勋章，在QQ音乐平台有机会抽取「众声漫游夜」音乐会门票，在酷狗音乐平台有机会抽取精美周边。\n本模块中奖者会收到系统弹窗提示，请注意填写信息。此外也可点击QQ音乐APP「我的」-「会员中心」-「我的资产」-「优惠券」进行查看和填写。\n\n3.活动期间，完成活动页内抽奖任务，在QQ音乐平台有机会抽取「众声漫游夜」音乐会门票，两平台均有机会抽取纯雨滴与养成材料。\n本模块门票中奖者会收到系统弹窗提示，请注意填写信息。此外也可点击QQ音乐APP「我的」-「会员中心」-「我的资产」-「优惠券」进行查看和填写。游戏资源以兑换码形式发放，可前往游戏内「设置」-「账户「-「兑换码」领取礼包。\n\n4. 活动期间，参与优质评论征集活动，被选中的优质乐评有机会登上「优质乐评」区域，在QQ音乐平台有机会获得「众声漫游夜」音乐会门票，在酷狗音乐平台有机会抽取精美周边。\n本模块中奖者将会收到音乐平台官方账号的私信，请注意査收。\n\n更多音乐活动请查看活动页面。\n\n▶▶温馨提示◀◀\n1.每个游戏ID仅可领取1次养成材料礼包、纯雨滴*30。（若QQ音乐与酷狗音乐重复获取兑换码，也仅可兑换1次）；\n2.每位用户每个抽奖任务仅限参与1次，在活动期间完成全部任务最多可获4次抽奖机会。（若QQ音乐与酷狗音乐重复抽取，也仅可兑换4次）；\n3.活动兑换码有效期截止至2026年8月15日23:59，请在有效期内进行兑换。\n4.抽奖活动道具数量有限，发完即止。\n*具体活动规则，请查看活动页面内“活动规则”。\n\n\n图文地址：https://www.bilibili.com/opus/1225957238824239160",
    "image": "",
    "images": [],
    "videos": [],
    "category": "活动",
    "important": false,
    "pinOrder": 999999,
    "pinExpiry": ""
  },
  {
    "id": 8042,
    "date": "2026-07-17",
    "time": "2026-07-17 09:00:09",
    "channel": "@MCKURO",
    "title": "《酣梦于彼岸深红》 | 《鸣潮》演唱会「致予新世界」\n\n“我愿意倾尽所有，\n再续上一天和你的时光。”",
    "text": "《酣梦于彼岸深红》 | 《鸣潮》演唱会「致予新世界」\n\n“我愿意倾尽所有，\n再续上一天和你的时光。”\n\n《鸣潮》巡回演唱会「致予新世界」线上直播将于2026年7月18日19:05正式播出。\n\nsource @MCKURO",
    "content": "《酣梦于彼岸深红》 | 《鸣潮》演唱会「致予新世界」\n\n“我愿意倾尽所有，\n再续上一天和你的时光。”\n\n《鸣潮》巡回演唱会「致予新世界」线上直播将于2026年7月18日19:05正式播出。\n\nsource @MCKURO",
    "image": "https://cora.jackie3137.xyz/f/6abddcd54ff2aa22c18e/Thunder%20File%20To%20Link_20260717090010.jpg",
    "images": [
      "https://cora.jackie3137.xyz/f/6abddcd54ff2aa22c18e/Thunder%20File%20To%20Link_20260717090010.jpg"
    ],
    "videos": [],
    "category": "活动",
    "important": false,
    "pinOrder": 999999,
    "pinExpiry": ""
  },
  {
    "id": 89,
    "date": "2026-07-17",
    "time": "2026-07-17 06:00:14",
    "channel": "@ENDFIELDBULLETINGPT",
    "title": "新游戏内公告：完成限时签到领取丰厚奖励\n#资讯速报",
    "text": "新游戏内公告：完成限时签到领取丰厚奖励\n#资讯速报",
    "content": "新游戏内公告：完成限时签到领取丰厚奖励\n#资讯速报",
    "image": "https://cora.jackie3137.xyz/f/24c1f78807ad8c638994/Thunder%20File%20To%20Link_20260717060015.jpg",
    "images": [
      "https://cora.jackie3137.xyz/f/24c1f78807ad8c638994/Thunder%20File%20To%20Link_20260717060015.jpg"
    ],
    "videos": [],
    "category": "活动",
    "important": false,
    "pinOrder": 999999,
    "pinExpiry": ""
  },
  {
    "id": 88,
    "date": "2026-07-17",
    "time": "2026-07-17 05:00:26",
    "channel": "@ENDFIELDBULLETINGPT",
    "title": "新游戏内公告：https://telegra.ph/向渊行版本创作征集活动进行中-07-17\n省流：",
    "text": "「向渊行」版本创作征集活动进行中\n管理员，《明日方舟：终末地》「向渊行」版本创作征集活动正在\n哔哩哔哩、抖音、小红书、微博、TapTap、虎牙、斗鱼、知乎\n等多个社区平台进行中。按对应要求进行内容创作与分享，即可参与奖金瓜分、创作评优与互动抽奖等活动，有机会赢取现金、平台激励与实体周边/3C产品等丰厚奖励。\n各平台活动时间安排请以对应平台活动页面内的规则公示为准。\n◆ 哔哩哔哩\n活动期间，在哔哩哔哩平台带话题\n#明日方舟终末地创作者应援计划\n或其他指定热门话题进行视频投稿，或在《明日方舟：终末地》直播分区进行直播，达成活动规定条件即可参与投稿瓜分及优秀稿件、主播榜单的评选，赢取现金及嵌晶玉、养成材料奖励。同时，您可以通过分享互动等完成抽奖任务，有机会获得养成材料、游戏周边与3C产品等丰厚奖励。\n点击跳转创作活动页面\n◆ 小红书\n活动期间，在小红书平台带话题\n#明日方舟终末地 #终末地向渊行\n及其他赛道话题进行笔记发布，即可参与创作激励赛道，参与瓜分和优秀笔记评选，赢取现金与游戏周边等丰厚奖励。同时，您也可以通过进行笔记互动等完成互动任务并参与抽奖，有机会获得游戏周边、3C产品等奖励。\n点击跳转创作活动页面\n◆ 微博\n活动期间，在微博平台带话题\n#明日方舟终末地创作征集#\n以及\n#向渊行#\n，发布以「\n向渊行\n」版本为主题的作品或讨论\n，\n即可参与创作征集活动，有机会获得嵌晶玉及现金等丰厚奖励。同时，您也可以在明日方舟终末地超话内带话题\n#明日方舟终末地二创#\n或\n#明日方舟终末地攻略#\n发布原创博文参与活动，达到条件即可参与瓜分现金奖励。\n点击跳转活动详情\n◆ 抖音\n即日起至活动结束，在抖音平台带话题\n#明日方舟终末地 #向渊行\n，并挂载《明日方舟：终末地》小手柄进行投稿，达到条件可参与瓜分活动，更有里程碑打卡、作者榜单评选等丰厚奖励，您还可参与互动抽奖，有机会获得游戏道具与3C产品等丰厚奖励。\n点击跳转投稿活动页面\n点击跳转抽奖活动页面\n◆ TapTap\n活动期间，在TapTap社区参与话题活动\n#终末地向渊行#\n并进行投稿，发布「\n向渊行\n」版本为主题的作品或讨论即可参与创作征集活动，有机会获得嵌晶玉、现金与游戏周边等丰厚奖励。\n点击跳转活动详情\n◆ 微信游戏圈\n活动期间，在微信游戏圈\n#向渊行#\n话题内参与「\n向渊行\n」版本游戏圈福利、话题讨论、每日签到、有奖盖楼等活动，完成指定任务即有机会获得嵌晶玉及实物周边等丰厚奖励。\n活动详情：具体可在【明日方舟终末地游戏圈】活动页面查看\n◆ 虎牙/斗鱼\n活动期间，在虎牙直播平台、斗鱼直播平台中的\n明日方舟：终末地专区\n进行直播，完成对应直播任务可享受主播激励计划的扶持。同时，您可通过观看直播、互动等方式参与抽奖，有机会获得养成材料及实物周边等丰厚奖励。\n点击跳转虎牙主播激励计划页面\n点击跳转斗鱼主播激励计划页面\n◆\n知乎\n活动期间，前往知乎搜索「明日方舟终末地」，参与创作激励计划，即有机会获得嵌晶玉和游戏周边好礼！更多详情可前往知乎活动页面查看。\n点击跳转活动详情\n更多活动详情与参与细则，请关注对应社区平台的活动发布。\n《明日方舟：终末地》将在未来持续为各位管理员的创作提供更全面的支持，感谢您的持续关注，祝您在塔卫二的探索一切顺利。",
    "content": "「向渊行」版本创作征集活动进行中\n管理员，《明日方舟：终末地》「向渊行」版本创作征集活动正在\n哔哩哔哩、抖音、小红书、微博、TapTap、虎牙、斗鱼、知乎\n等多个社区平台进行中。按对应要求进行内容创作与分享，即可参与奖金瓜分、创作评优与互动抽奖等活动，有机会赢取现金、平台激励与实体周边/3C产品等丰厚奖励。\n各平台活动时间安排请以对应平台活动页面内的规则公示为准。\n◆ 哔哩哔哩\n活动期间，在哔哩哔哩平台带话题\n#明日方舟终末地创作者应援计划\n或其他指定热门话题进行视频投稿，或在《明日方舟：终末地》直播分区进行直播，达成活动规定条件即可参与投稿瓜分及优秀稿件、主播榜单的评选，赢取现金及嵌晶玉、养成材料奖励。同时，您可以通过分享互动等完成抽奖任务，有机会获得养成材料、游戏周边与3C产品等丰厚奖励。\n点击跳转创作活动页面\n◆ 小红书\n活动期间，在小红书平台带话题\n#明日方舟终末地 #终末地向渊行\n及其他赛道话题进行笔记发布，即可参与创作激励赛道，参与瓜分和优秀笔记评选，赢取现金与游戏周边等丰厚奖励。同时，您也可以通过进行笔记互动等完成互动任务并参与抽奖，有机会获得游戏周边、3C产品等奖励。\n点击跳转创作活动页面\n◆ 微博\n活动期间，在微博平台带话题\n#明日方舟终末地创作征集#\n以及\n#向渊行#\n，发布以「\n向渊行\n」版本为主题的作品或讨论\n，\n即可参与创作征集活动，有机会获得嵌晶玉及现金等丰厚奖励。同时，您也可以在明日方舟终末地超话内带话题\n#明日方舟终末地二创#\n或\n#明日方舟终末地攻略#\n发布原创博文参与活动，达到条件即可参与瓜分现金奖励。\n点击跳转活动详情\n◆ 抖音\n即日起至活动结束，在抖音平台带话题\n#明日方舟终末地 #向渊行\n，并挂载《明日方舟：终末地》小手柄进行投稿，达到条件可参与瓜分活动，更有里程碑打卡、作者榜单评选等丰厚奖励，您还可参与互动抽奖，有机会获得游戏道具与3C产品等丰厚奖励。\n点击跳转投稿活动页面\n点击跳转抽奖活动页面\n◆ TapTap\n活动期间，在TapTap社区参与话题活动\n#终末地向渊行#\n并进行投稿，发布「\n向渊行\n」版本为主题的作品或讨论即可参与创作征集活动，有机会获得嵌晶玉、现金与游戏周边等丰厚奖励。\n点击跳转活动详情\n◆ 微信游戏圈\n活动期间，在微信游戏圈\n#向渊行#\n话题内参与「\n向渊行\n」版本游戏圈福利、话题讨论、每日签到、有奖盖楼等活动，完成指定任务即有机会获得嵌晶玉及实物周边等丰厚奖励。\n活动详情：具体可在【明日方舟终末地游戏圈】活动页面查看\n◆ 虎牙/斗鱼\n活动期间，在虎牙直播平台、斗鱼直播平台中的\n明日方舟：终末地专区\n进行直播，完成对应直播任务可享受主播激励计划的扶持。同时，您可通过观看直播、互动等方式参与抽奖，有机会获得养成材料及实物周边等丰厚奖励。\n点击跳转虎牙主播激励计划页面\n点击跳转斗鱼主播激励计划页面\n◆\n知乎\n活动期间，前往知乎搜索「明日方舟终末地」，参与创作激励计划，即有机会获得嵌晶玉和游戏周边好礼！更多详情可前往知乎活动页面查看。\n点击跳转活动详情\n更多活动详情与参与细则，请关注对应社区平台的活动发布。\n《明日方舟：终末地》将在未来持续为各位管理员的创作提供更全面的支持，感谢您的持续关注，祝您在塔卫二的探索一切顺利。",
    "image": "https://cora.jackie3137.xyz/f/be6b996532436a7a31f3/Thunder%20File%20To%20Link_20260717050032.jpg",
    "images": [
      "https://cora.jackie3137.xyz/f/be6b996532436a7a31f3/Thunder%20File%20To%20Link_20260717050032.jpg"
    ],
    "videos": [],
    "category": "活动",
    "important": false,
    "pinOrder": 999999,
    "pinExpiry": ""
  },
  {
    "id": 6689,
    "date": "2026-07-17",
    "time": "2026-07-17 04:10:22",
    "channel": "@YUANSHEN",
    "title": "@YUANSHEN",
    "text": "",
    "content": "",
    "image": "https://cora.jackie3137.xyz/f/3016bb7e07c2a0e284d4/Thunder%20File%20To%20Link_20260717041124.jpg",
    "images": [
      "https://cora.jackie3137.xyz/f/3016bb7e07c2a0e284d4/Thunder%20File%20To%20Link_20260717041124.jpg",
      "https://cora.jackie3137.xyz/f/b2be75e0f92c61fe948d/Thunder%20File%20To%20Link_20260717041355.jpg",
      "https://cora.jackie3137.xyz/f/f3555a866323d43e17cf/Thunder%20File%20To%20Link_20260717041642.jpg",
      "https://cora.jackie3137.xyz/f/42682c83f61c6281a5b2/Thunder%20File%20To%20Link_20260717041732.jpg",
      "https://cora.jackie3137.xyz/f/382881e9e601f31d3916/Thunder%20File%20To%20Link_20260717041822.jpg",
      "https://cora.jackie3137.xyz/f/6debeb7d1806d6499566/Thunder%20File%20To%20Link_20260717041912.jpg",
      "https://cora.jackie3137.xyz/f/30953a1c025850cbeec8/Thunder%20File%20To%20Link_20260717042003.jpg",
      "https://cora.jackie3137.xyz/f/40bd5d48ca6191991d94/Thunder%20File%20To%20Link_20260717042053.jpg",
      "https://cora.jackie3137.xyz/f/4747e62bb6eb5ab5277a/Thunder%20File%20To%20Link_20260717042143.jpg",
      "https://cora.jackie3137.xyz/f/3d406333c6a59b139ad8/Thunder%20File%20To%20Link_20260717042233.jpg"
    ],
    "videos": [],
    "category": "活动",
    "important": false,
    "pinOrder": 999999,
    "pinExpiry": ""
  },
  {
    "id": 130108,
    "date": "2026-07-17",
    "time": "2026-07-17 04:05:13",
    "channel": "@REVERSE1999CN",
    "title": "重返未来1999\n\n#重返未来1999# #重返未来原子之心联动# #重返未来联动# \n//衣着上新",
    "text": "重返未来1999\n\n#重返未来1999# #重返未来原子之心联动# #重返未来联动# \n//衣着上新\n可编程挽歌 | Programmed Eulogy\n*装置式未来*系列，双生舞伶全新衣着。\n一圈、再一圈挥鞭转，机械天鹅不会流出真心的眼泪吗？\n\n▶▶衣着宣传折页◀◀\n※全新神秘术特效\n※全新箱中姿态\n※“尤提姆”新装\n※全新释放神秘术语音、音效\n※全新Live2D交互动作×2\n※全新战斗入场效果\n※全新荒原动作\n※崭新形象\n※崭新单品×3 \n\n▶▶获取途径◀◀\n7/23 10:00 - 8/13 4:59，双生舞伶新增衣着「可编程挽歌」将在【衣着风尚】商店上架并限时售卖。\n\n\n图文地址：https://www.bilibili.com/opus/1225879875722674181",
    "content": "重返未来1999\n\n#重返未来1999# #重返未来原子之心联动# #重返未来联动# \n//衣着上新\n可编程挽歌 | Programmed Eulogy\n*装置式未来*系列，双生舞伶全新衣着。\n一圈、再一圈挥鞭转，机械天鹅不会流出真心的眼泪吗？\n\n▶▶衣着宣传折页◀◀\n※全新神秘术特效\n※全新箱中姿态\n※“尤提姆”新装\n※全新释放神秘术语音、音效\n※全新Live2D交互动作×2\n※全新战斗入场效果\n※全新荒原动作\n※崭新形象\n※崭新单品×3 \n\n▶▶获取途径◀◀\n7/23 10:00 - 8/13 4:59，双生舞伶新增衣着「可编程挽歌」将在【衣着风尚】商店上架并限时售卖。\n\n\n图文地址：https://www.bilibili.com/opus/1225879875722674181",
    "image": "https://cora.jackie3137.xyz/f/181c56d9775daad885a6/Thunder%20File%20To%20Link_20260717040533.jpg",
    "images": [
      "https://cora.jackie3137.xyz/f/181c56d9775daad885a6/Thunder%20File%20To%20Link_20260717040533.jpg",
      "https://cora.jackie3137.xyz/f/d2382676b6f200dcf724/Thunder%20File%20To%20Link_20260717040623.jpg",
      "https://cora.jackie3137.xyz/f/8172fde128332f6b27df/Thunder%20File%20To%20Link_20260717040713.jpg",
      "https://cora.jackie3137.xyz/f/cc7495d8a8f2ad1b8d7e/Thunder%20File%20To%20Link_20260717040804.jpg",
      "https://cora.jackie3137.xyz/f/3f4333522449e6abf38c/Thunder%20File%20To%20Link_20260717040854.jpg",
      "https://cora.jackie3137.xyz/f/d691df7a557e82d31201/Thunder%20File%20To%20Link_20260717040944.jpg",
      "https://cora.jackie3137.xyz/f/7b861ef94dd2cc6aeefc/Thunder%20File%20To%20Link_20260717041034.jpg",
      "https://cora.jackie3137.xyz/f/795682afe39d5f063aa2/Thunder%20File%20To%20Link_20260717041305.jpg",
      "https://cora.jackie3137.xyz/f/e2faa66a98dd349d1e52/Thunder%20File%20To%20Link_20260717041544.jpg"
    ],
    "videos": [],
    "category": "活动",
    "important": false,
    "pinOrder": 999999,
    "pinExpiry": ""
  },
  {
    "id": 6691,
    "date": "2026-07-17",
    "time": "2026-07-17 04:10:31",
    "channel": "@YUANSHEN",
    "title": "《原神》「仲夏派对」快闪新情报揭晓\n\n亲爱的旅行者，《原神》「仲夏派对」快闪新情报今日正式揭晓！\n【",
    "text": "《原神》「仲夏派对」快闪新情报揭晓\n\n亲爱的旅行者，《原神》「仲夏派对」快闪新情报今日正式揭晓！\n【嘉宾活动】\n7月24日-7月28日，快闪现场将有特邀嘉宾或一日店长出没，本次活动为免预约入场，来活动现场发现他们的身影吧！\n【悠享周末活动】\n8月1日-8月2日、8月8日-8月9日，参加「泳圈派对」，赢周边好礼。\n【大屏及气模打卡攻略】\n线下将有多处大屏及角色气模等待旅行者打卡！\n【人气周边同步贩售】\n除「仲夏派对」系列周边外，本次快闪还将贩售多款人气周边，同享线下特别满赠哦~\n\nsource @YuanShen",
    "content": "《原神》「仲夏派对」快闪新情报揭晓\n\n亲爱的旅行者，《原神》「仲夏派对」快闪新情报今日正式揭晓！\n【嘉宾活动】\n7月24日-7月28日，快闪现场将有特邀嘉宾或一日店长出没，本次活动为免预约入场，来活动现场发现他们的身影吧！\n【悠享周末活动】\n8月1日-8月2日、8月8日-8月9日，参加「泳圈派对」，赢周边好礼。\n【大屏及气模打卡攻略】\n线下将有多处大屏及角色气模等待旅行者打卡！\n【人气周边同步贩售】\n除「仲夏派对」系列周边外，本次快闪还将贩售多款人气周边，同享线下特别满赠哦~\n\nsource @YuanShen",
    "image": "https://cora.jackie3137.xyz/f/48508cec33a5f02efbdd/Thunder%20File%20To%20Link_20260717041215.jpg",
    "images": [
      "https://cora.jackie3137.xyz/f/48508cec33a5f02efbdd/Thunder%20File%20To%20Link_20260717041215.jpg",
      "https://cora.jackie3137.xyz/f/aa9553075bfd9382a285/Thunder%20File%20To%20Link_20260717041445.jpg"
    ],
    "videos": [],
    "category": "活动",
    "important": false,
    "pinOrder": 999999,
    "pinExpiry": ""
  },
  {
    "id": 87,
    "date": "2026-07-17",
    "time": "2026-07-17 04:00:14",
    "channel": "@ENDFIELDBULLETINGPT",
    "title": "新游戏内公告：渊客停系列衍生品现已开售\n#资讯速报",
    "text": "新游戏内公告：渊客停系列衍生品现已开售\n#资讯速报",
    "content": "新游戏内公告：渊客停系列衍生品现已开售\n#资讯速报",
    "image": "https://cora.jackie3137.xyz/f/4c07e32f2a73d38c7c41/Thunder%20File%20To%20Link_20260717040015.jpg",
    "images": [
      "https://cora.jackie3137.xyz/f/4c07e32f2a73d38c7c41/Thunder%20File%20To%20Link_20260717040015.jpg"
    ],
    "videos": [],
    "category": "活动",
    "important": false,
    "pinOrder": 999999,
    "pinExpiry": ""
  },
  {
    "id": 8039,
    "date": "2026-07-17",
    "time": "2026-07-17 03:00:07",
    "channel": "@MCKURO",
    "title": "共鸣者档案前瞻 | 清宵\n\n\"前路难测，别离我太远。\"\n\n共鸣属性：气动\n武器类型：迅刀\n\nsour",
    "text": "共鸣者档案前瞻 | 清宵\n\n\"前路难测，别离我太远。\"\n\n共鸣属性：气动\n武器类型：迅刀\n\nsource @MCKURO",
    "content": "共鸣者档案前瞻 | 清宵\n\n\"前路难测，别离我太远。\"\n\n共鸣属性：气动\n武器类型：迅刀\n\nsource @MCKURO",
    "image": "https://cora.jackie3137.xyz/f/f6938c11e07d48c19de9/Thunder%20File%20To%20Link_20260717030019.jpg",
    "images": [
      "https://cora.jackie3137.xyz/f/f6938c11e07d48c19de9/Thunder%20File%20To%20Link_20260717030019.jpg",
      "https://cora.jackie3137.xyz/f/2a205a5ae7034da617a6/Thunder%20File%20To%20Link_20260717030159.jpg"
    ],
    "videos": [],
    "category": "活动",
    "important": false,
    "pinOrder": 999999,
    "pinExpiry": ""
  },
  {
    "id": 86,
    "date": "2026-07-17",
    "time": "2026-07-17 03:00:25",
    "channel": "@ENDFIELDBULLETINGPT",
    "title": "新游戏内公告：https://telegra.ph/向渊行版本更新修复说明-07-17\n省流：公告发",
    "text": "「向渊行」版本更新修复说明\n亲爱的管理员：\n为了给大家带来更好的游戏体验，我们将对游戏持续进行优化及问题修复。「向渊行」版本期间更新修复说明如下：\n▼//游戏更新修复说明\n■ 2026/07/17\n· 优化了特定操作下，6星干员【诀】重击时的动态表现。\n· 优化了委派任务「日常·失落机器人」战斗环节的镜头逻辑。\n· 优化了「武陵 - 北部禁区」中，部分剧情对话时场景的表现。\n· 优化了【活动中心】部分活动页签的展示排序。\n· 优化了部分任务的场景特效表现。\n· 修复了特定情况下，主线任务「第二章 - 进程Ⅶ - 归途之始」中，有概率无法【与庄方宜交谈】导致无法推进任务流程的问题。\n· 修复了特定情况下，主线任务「第二章 - 进程Ⅶ - 归途之始」中，无法正常使用【赤铜耐压罐】收集「惰气」的问题。\n· 修复了使用移动端设备时，6星干员【诀】释放【破晦诀明】后，终结技能量进度显示异常的问题。\n· 修复了在与交互物互动时，非主控干员无法正常释放技能的问题。\n· 修复了特定情况下，在「武陵 - 北部禁区」特定暂存能量淤积点中离开挑战范围后，无法正常中止挑战的问题。\n· 修复了在「武陵」部分区域内通过特定操作打开设备制造页面时，导致界面卡死的问题。\n· 修复了特定情况下，可以异常使用【拍照】模式的移动站位功能的问题。\n· 修复了特定情况下，在【拍照】模式下特定操作导致干员状态异常的问题。\n· 修复了特定情况下，无法完成【简易制作 - 随身装置】相关引导的问题。\n· 修复了特定情况下，特定操作有概率导致在「武陵 - 应龙关」区域的特定范围内游戏界面持续弹出提示信息的问题。\n· 修复了特定情况下，特定操作有概率导致玩法「战争回响」的教学引导弹窗显示异常的问题。\n· 修复了【百相仪】玩法中，特定情况下提示信息未正常弹出的问题。\n· 修复了特定情况下，部分场景中特定物品模型异常不显示的问题。\n· 修复了特定情况下，【贵重品库】红点显示异常的问题。\n如遇到其他问题，还请管理员通过游戏内客服等方式提供反馈。\n期间带来的不便我们深表歉意，再次感谢管理员对《明日方舟：终末地》一直以来的关注与支持！",
    "content": "「向渊行」版本更新修复说明\n亲爱的管理员：\n为了给大家带来更好的游戏体验，我们将对游戏持续进行优化及问题修复。「向渊行」版本期间更新修复说明如下：\n▼//游戏更新修复说明\n■ 2026/07/17\n· 优化了特定操作下，6星干员【诀】重击时的动态表现。\n· 优化了委派任务「日常·失落机器人」战斗环节的镜头逻辑。\n· 优化了「武陵 - 北部禁区」中，部分剧情对话时场景的表现。\n· 优化了【活动中心】部分活动页签的展示排序。\n· 优化了部分任务的场景特效表现。\n· 修复了特定情况下，主线任务「第二章 - 进程Ⅶ - 归途之始」中，有概率无法【与庄方宜交谈】导致无法推进任务流程的问题。\n· 修复了特定情况下，主线任务「第二章 - 进程Ⅶ - 归途之始」中，无法正常使用【赤铜耐压罐】收集「惰气」的问题。\n· 修复了使用移动端设备时，6星干员【诀】释放【破晦诀明】后，终结技能量进度显示异常的问题。\n· 修复了在与交互物互动时，非主控干员无法正常释放技能的问题。\n· 修复了特定情况下，在「武陵 - 北部禁区」特定暂存能量淤积点中离开挑战范围后，无法正常中止挑战的问题。\n· 修复了在「武陵」部分区域内通过特定操作打开设备制造页面时，导致界面卡死的问题。\n· 修复了特定情况下，可以异常使用【拍照】模式的移动站位功能的问题。\n· 修复了特定情况下，在【拍照】模式下特定操作导致干员状态异常的问题。\n· 修复了特定情况下，无法完成【简易制作 - 随身装置】相关引导的问题。\n· 修复了特定情况下，特定操作有概率导致在「武陵 - 应龙关」区域的特定范围内游戏界面持续弹出提示信息的问题。\n· 修复了特定情况下，特定操作有概率导致玩法「战争回响」的教学引导弹窗显示异常的问题。\n· 修复了【百相仪】玩法中，特定情况下提示信息未正常弹出的问题。\n· 修复了特定情况下，部分场景中特定物品模型异常不显示的问题。\n· 修复了特定情况下，【贵重品库】红点显示异常的问题。\n如遇到其他问题，还请管理员通过游戏内客服等方式提供反馈。\n期间带来的不便我们深表歉意，再次感谢管理员对《明日方舟：终末地》一直以来的关注与支持！",
    "image": "https://cora.jackie3137.xyz/f/54dae4bb36928858c09f/Thunder%20File%20To%20Link_20260717030109.jpg",
    "images": [
      "https://cora.jackie3137.xyz/f/54dae4bb36928858c09f/Thunder%20File%20To%20Link_20260717030109.jpg"
    ],
    "videos": [],
    "category": "活动",
    "important": false,
    "pinOrder": 999999,
    "pinExpiry": ""
  },
  {
    "id": 1311,
    "date": "2026-07-17",
    "time": "2026-07-17 03:01:15",
    "channel": "@ARKBULLETIN_CN",
    "title": "新游戏内公告：https://telegra.ph/07月17日1600闪断更新公告-07-17\n省",
    "text": "07月17日16:00闪断更新公告\n感谢您对《明日方舟》的关注与支持。《明日方舟》计划将于2026年07月17日16:00 ~ 16:10期间进行服务器闪断更新。届时将造成玩家强制掉线，无法登录等问题。为确保您的游戏内账号数据正常，请在本次闪断更新时提前结束关卡。本次更新给各位玩家带来的不便，敬请谅解！\n闪断更新时间：\n2026年07月17日16:00 ~ 16:10 期间\n更新内容：\n◆集成战略全新主题【沉沦者的黑流树海】开启，详情请参照官方自媒体相关介绍\n◆07月20日04:00 SideStory「红丝绒」限时复刻资源预载，详情请参照官方相关公告\n◆07月20日04:00【我们明日见】记录修复资源预载\n◆家具商店新增常驻售卖家具【“玫瑰河畔安全屋”】（07月20日04:00起）\n◆07月23日04:00【中坚寻访】更新资源预载\n◆07月23日04:00【采购中心-通用凭证区&高级凭证区】更新（可兑换干员：安洁莉娜、乌有）资源预载\n◆07月30日04:00常驻【标准寻访】更新资源预载\n◆07月30日04:00【采购中心-高级凭证区】更新（可兑换干员：琳琅诗怀雅、子月）资源预载\n◆新剿灭作战关卡【默祷圣祠】资源预载\n开启时间：07月27日 04:00 - 10月26日 03:59\n开启说明：新增剿灭委托关卡【默祷圣祠】将替换现有剿灭委托关卡【朱墙食府】，现剿灭委托关卡【朱墙食府】将在关闭后收录进假定作战目标\n◆08月01日04:00集成战略主题【沉沦者的黑流树海】源流堆栈、实践者列表及委托任务更新资源预载\n◆修复干员【佩德洛】技能「交替撤离」施加于友方单位的触发型效果特定情况下效果异常的问题\n◆修复干员【佩德洛】天赋「掩护战术」部分情况下效果异常的问题\n闪断补偿：\n合成玉*200\n补偿范围：\n2026年07月17日16:00更新前所有注册并创建角色的玩家\n*本次维护不排除延迟开启的可能，如若延迟则请关注官方发布的具体开服时间*\n【明日方舟】运营组\n2026年07月17日",
    "content": "07月17日16:00闪断更新公告\n感谢您对《明日方舟》的关注与支持。《明日方舟》计划将于2026年07月17日16:00 ~ 16:10期间进行服务器闪断更新。届时将造成玩家强制掉线，无法登录等问题。为确保您的游戏内账号数据正常，请在本次闪断更新时提前结束关卡。本次更新给各位玩家带来的不便，敬请谅解！\n闪断更新时间：\n2026年07月17日16:00 ~ 16:10 期间\n更新内容：\n◆集成战略全新主题【沉沦者的黑流树海】开启，详情请参照官方自媒体相关介绍\n◆07月20日04:00 SideStory「红丝绒」限时复刻资源预载，详情请参照官方相关公告\n◆07月20日04:00【我们明日见】记录修复资源预载\n◆家具商店新增常驻售卖家具【“玫瑰河畔安全屋”】（07月20日04:00起）\n◆07月23日04:00【中坚寻访】更新资源预载\n◆07月23日04:00【采购中心-通用凭证区&高级凭证区】更新（可兑换干员：安洁莉娜、乌有）资源预载\n◆07月30日04:00常驻【标准寻访】更新资源预载\n◆07月30日04:00【采购中心-高级凭证区】更新（可兑换干员：琳琅诗怀雅、子月）资源预载\n◆新剿灭作战关卡【默祷圣祠】资源预载\n开启时间：07月27日 04:00 - 10月26日 03:59\n开启说明：新增剿灭委托关卡【默祷圣祠】将替换现有剿灭委托关卡【朱墙食府】，现剿灭委托关卡【朱墙食府】将在关闭后收录进假定作战目标\n◆08月01日04:00集成战略主题【沉沦者的黑流树海】源流堆栈、实践者列表及委托任务更新资源预载\n◆修复干员【佩德洛】技能「交替撤离」施加于友方单位的触发型效果特定情况下效果异常的问题\n◆修复干员【佩德洛】天赋「掩护战术」部分情况下效果异常的问题\n闪断补偿：\n合成玉*200\n补偿范围：\n2026年07月17日16:00更新前所有注册并创建角色的玩家\n*本次维护不排除延迟开启的可能，如若延迟则请关注官方发布的具体开服时间*\n【明日方舟】运营组\n2026年07月17日",
    "image": "",
    "images": [],
    "videos": [],
    "category": "活动",
    "important": false,
    "pinOrder": 999999,
    "pinExpiry": ""
  },
  {
    "id": 8037,
    "date": "2026-07-16",
    "time": "2026-07-16 17:00:14",
    "channel": "@MCKURO",
    "title": "《鸣潮》巡回演唱会「致予新世界」| 首日返图\n\n致予新世界的旋律，今夜正式奏响。\n感谢漂泊者的到来，",
    "text": "《鸣潮》巡回演唱会「致予新世界」| 首日返图\n\n致予新世界的旋律，今夜正式奏响。\n感谢漂泊者的到来，我们明天再见！\n\nsource @MCKURO",
    "content": "《鸣潮》巡回演唱会「致予新世界」| 首日返图\n\n致予新世界的旋律，今夜正式奏响。\n感谢漂泊者的到来，我们明天再见！\n\nsource @MCKURO",
    "image": "https://cora.jackie3137.xyz/f/b36fe9f0a3a4c9ab3e14/Thunder%20File%20To%20Link_20260716170029.jpg",
    "images": [
      "https://cora.jackie3137.xyz/f/b36fe9f0a3a4c9ab3e14/Thunder%20File%20To%20Link_20260716170029.jpg",
      "https://cora.jackie3137.xyz/f/1036c107d907d64eb2c8/Thunder%20File%20To%20Link_20260716170119.jpg",
      "https://cora.jackie3137.xyz/f/520e7168c57693b078e2/Thunder%20File%20To%20Link_20260716170209.jpg",
      "https://cora.jackie3137.xyz/f/1196cf2d1ce75bae0ca2/Thunder%20File%20To%20Link_20260716170300.jpg",
      "https://cora.jackie3137.xyz/f/67f28e7ae8ea0d6167ba/Thunder%20File%20To%20Link_20260716170350.jpg",
      "https://cora.jackie3137.xyz/f/b7ceb92c1ef891694205/Thunder%20File%20To%20Link_20260716170441.jpg",
      "https://cora.jackie3137.xyz/f/d6b3fd338af7229bcd49/Thunder%20File%20To%20Link_20260716170533.jpg",
      "https://cora.jackie3137.xyz/f/3684e766c6ac97410cb1/Thunder%20File%20To%20Link_20260716170624.jpg",
      "https://cora.jackie3137.xyz/f/d68bed3340273ff77af5/Thunder%20File%20To%20Link_20260716170715.jpg"
    ],
    "videos": [],
    "category": "活动",
    "important": false,
    "pinOrder": 999999,
    "pinExpiry": ""
  },
  {
    "id": 848,
    "date": "2026-07-16",
    "time": "2026-07-16 09:03:02",
    "channel": "@ARKTIPS",
    "title": "26.7.16\n活动【丛林症结】将于7.16日28:00结束。\n本周理智药可以直接用完哦~\n记得检查",
    "text": "26.7.16\n活动【丛林症结】将于7.16日28:00结束。\n本周理智药可以直接用完哦~\n记得检查一下蚀刻章是否完成~",
    "content": "26.7.16\n活动【丛林症结】将于7.16日28:00结束。\n本周理智药可以直接用完哦~\n记得检查一下蚀刻章是否完成~",
    "image": "",
    "images": [],
    "videos": [],
    "category": "活动",
    "important": false,
    "pinOrder": 999999,
    "pinExpiry": ""
  },
  {
    "id": 6674,
    "date": "2026-07-16",
    "time": "2026-07-16 08:12:11",
    "channel": "@YUANSHEN",
    "title": "「映夏！归乡？千灵节！」「月之八」版本活动速递第二期\n\n旅行者好呀~一起来看看近期都有哪些活动吧！\n",
    "text": "「映夏！归乡？千灵节！」「月之八」版本活动速递第二期\n\n旅行者好呀~一起来看看近期都有哪些活动吧！\n活动「映夏！归乡？千灵节！」、区域探索限时奖励活动「当我们抬头望月亮」还在进行中哦，没有领取奖励的旅行者千万不要错过。\n点击了解更多「月之八」版本内容：\n>>原神「『空月之歌·谐谑』映夏！归乡？千灵节！」内容专题页<<\n\nsource @YuanShen #版本活动速递",
    "content": "「映夏！归乡？千灵节！」「月之八」版本活动速递第二期\n\n旅行者好呀~一起来看看近期都有哪些活动吧！\n活动「映夏！归乡？千灵节！」、区域探索限时奖励活动「当我们抬头望月亮」还在进行中哦，没有领取奖励的旅行者千万不要错过。\n点击了解更多「月之八」版本内容：\n>>原神「『空月之歌·谐谑』映夏！归乡？千灵节！」内容专题页<<\n\nsource @YuanShen #版本活动速递",
    "image": "https://cora.jackie3137.xyz/f/f2d6bf06bd5c31b43955/Thunder%20File%20To%20Link_20260716081223.jpg",
    "images": [
      "https://cora.jackie3137.xyz/f/f2d6bf06bd5c31b43955/Thunder%20File%20To%20Link_20260716081223.jpg",
      "https://cora.jackie3137.xyz/f/3d5833e693509bdda3b2/Thunder%20File%20To%20Link_20260716081313.jpg",
      "https://cora.jackie3137.xyz/f/54cad14d43aab3b64d01/Thunder%20File%20To%20Link_20260716081403.jpg",
      "https://cora.jackie3137.xyz/f/1f7b69acaa3fed3654e9/Thunder%20File%20To%20Link_20260716081454.jpg",
      "https://cora.jackie3137.xyz/f/9e73fb9510c8ca0d9abb/Thunder%20File%20To%20Link_20260716081545.jpg",
      "https://cora.jackie3137.xyz/f/d35e91d224aaff8147e6/Thunder%20File%20To%20Link_20260716081636.jpg",
      "https://cora.jackie3137.xyz/f/e16ff246831708a9ee3e/Thunder%20File%20To%20Link_20260716081726.jpg"
    ],
    "videos": [],
    "category": "活动",
    "important": false,
    "pinOrder": 999999,
    "pinExpiry": ""
  },
  {
    "id": 6667,
    "date": "2026-07-16",
    "time": "2026-07-16 08:02:15",
    "channel": "@YUANSHEN",
    "title": "祈愿：「法器·帷间夜曲」「长柄武器·薙草之稻光」概率UP！\n\n活动期间，旅行者可以在「神铸赋形」活动",
    "text": "祈愿：「法器·帷间夜曲」「长柄武器·薙草之稻光」概率UP！\n\n活动期间，旅行者可以在「神铸赋形」活动祈愿中获得更多武器与角色，提升队伍的战斗力！\n \n〓祈愿介绍〓\n●活动期间，限定5星武器「法器·帷间夜曲」「长柄武器·薙草之稻光」的祈愿获取概率将大幅提升！\n●活动期间，限定4星武器「法器·乘浪的回旋」、4星武器 「单手剑·祭礼剑」「双手剑·钟剑」「长柄武器·西风长枪」「弓·西风猎弓」的祈愿获取概率将大幅提升！\n●活动期间，可使用「神铸定轨」对本期5星UP武器「法器·帷间夜曲」或「长柄武器·薙草之稻光」进行定轨，更多「神铸定轨」详细规则可点击祈愿界面左下角【详情】按钮进行查询。\n※ 以上武器中，限定武器不会进入「奔行世间」常驻祈愿。\n\n※ 更多祈愿信息可点击祈愿界面左下角【详情】按钮进行查询。\n\nsource @YuanShen",
    "content": "祈愿：「法器·帷间夜曲」「长柄武器·薙草之稻光」概率UP！\n\n活动期间，旅行者可以在「神铸赋形」活动祈愿中获得更多武器与角色，提升队伍的战斗力！\n \n〓祈愿介绍〓\n●活动期间，限定5星武器「法器·帷间夜曲」「长柄武器·薙草之稻光」的祈愿获取概率将大幅提升！\n●活动期间，限定4星武器「法器·乘浪的回旋」、4星武器 「单手剑·祭礼剑」「双手剑·钟剑」「长柄武器·西风长枪」「弓·西风猎弓」的祈愿获取概率将大幅提升！\n●活动期间，可使用「神铸定轨」对本期5星UP武器「法器·帷间夜曲」或「长柄武器·薙草之稻光」进行定轨，更多「神铸定轨」详细规则可点击祈愿界面左下角【详情】按钮进行查询。\n※ 以上武器中，限定武器不会进入「奔行世间」常驻祈愿。\n\n※ 更多祈愿信息可点击祈愿界面左下角【详情】按钮进行查询。\n\nsource @YuanShen",
    "image": "https://cora.jackie3137.xyz/f/af3187139032a2149bb7/Thunder%20File%20To%20Link_20260716080358.jpg",
    "images": [
      "https://cora.jackie3137.xyz/f/af3187139032a2149bb7/Thunder%20File%20To%20Link_20260716080358.jpg",
      "https://cora.jackie3137.xyz/f/cd630e0626fc93cb3e91/Thunder%20File%20To%20Link_20260716080647.jpg"
    ],
    "videos": [],
    "category": "活动",
    "important": false,
    "pinOrder": 999999,
    "pinExpiry": ""
  },
  {
    "id": 6665,
    "date": "2026-07-16",
    "time": "2026-07-16 08:02:11",
    "channel": "@YUANSHEN",
    "title": "「影寂天下人」祈愿：「一心净土·雷电将军(雷)」概率UP！\n\n活动期间，旅行者可以在活动祈愿中获得更",
    "text": "「影寂天下人」祈愿：「一心净土·雷电将军(雷)」概率UP！\n\n活动期间，旅行者可以在活动祈愿中获得更多角色与武器，组建强大的队伍！\n \n〓祈愿介绍〓\n●活动期间，限定5星角色「一心净土·雷电将军(雷)」的祈愿获取概率将大幅提升！\n●活动期间，4星角色「系风攘影·雅珂达(风)」「深黯的谜烟·欧洛伦(雷)」「衡明知度·赛索斯(雷)」的祈愿获取概率将大幅提升！\n※ 以上角色中，限定角色不会进入「奔行世间」常驻祈愿。\n※ 本祈愿属于「角色活动祈愿-2」，「角色活动祈愿」和「角色活动祈愿-2」的祈愿次数保底完全共享，会一直共同累计在「角色活动祈愿」和「角色活动祈愿-2」中，与其他祈愿的祈愿次数保底相互独立计算，互不影响。\n※ 祈愿开启期间，还将开启相应的「且试身手」角色试用活动，旅行者可以使用包含试用角色的固定阵容进入指定的关卡进行体验，挑战成功后即可获得对应奖励！\n\n※ 更多祈愿信息可点击祈愿界面左下角【详情】按钮进行查询。\n\nsource @YuanShen",
    "content": "「影寂天下人」祈愿：「一心净土·雷电将军(雷)」概率UP！\n\n活动期间，旅行者可以在活动祈愿中获得更多角色与武器，组建强大的队伍！\n \n〓祈愿介绍〓\n●活动期间，限定5星角色「一心净土·雷电将军(雷)」的祈愿获取概率将大幅提升！\n●活动期间，4星角色「系风攘影·雅珂达(风)」「深黯的谜烟·欧洛伦(雷)」「衡明知度·赛索斯(雷)」的祈愿获取概率将大幅提升！\n※ 以上角色中，限定角色不会进入「奔行世间」常驻祈愿。\n※ 本祈愿属于「角色活动祈愿-2」，「角色活动祈愿」和「角色活动祈愿-2」的祈愿次数保底完全共享，会一直共同累计在「角色活动祈愿」和「角色活动祈愿-2」中，与其他祈愿的祈愿次数保底相互独立计算，互不影响。\n※ 祈愿开启期间，还将开启相应的「且试身手」角色试用活动，旅行者可以使用包含试用角色的固定阵容进入指定的关卡进行体验，挑战成功后即可获得对应奖励！\n\n※ 更多祈愿信息可点击祈愿界面左下角【详情】按钮进行查询。\n\nsource @YuanShen",
    "image": "https://cora.jackie3137.xyz/f/c29d95401480093da8fa/Thunder%20File%20To%20Link_20260716080308.jpg",
    "images": [
      "https://cora.jackie3137.xyz/f/c29d95401480093da8fa/Thunder%20File%20To%20Link_20260716080308.jpg",
      "https://cora.jackie3137.xyz/f/0346565859c1b43a2dab/Thunder%20File%20To%20Link_20260716080547.jpg"
    ],
    "videos": [],
    "category": "活动",
    "important": false,
    "pinOrder": 999999,
    "pinExpiry": ""
  },
  {
    "id": 6663,
    "date": "2026-07-16",
    "time": "2026-07-16 08:02:07",
    "channel": "@YUANSHEN",
    "title": "「伴月同眠」祈愿：「空月归乡·哥伦比娅(水)」概率UP！\n\n活动期间，旅行者可以在活动祈愿中获得更多",
    "text": "「伴月同眠」祈愿：「空月归乡·哥伦比娅(水)」概率UP！\n\n活动期间，旅行者可以在活动祈愿中获得更多角色与武器，组建强大的队伍！\n \n〓祈愿介绍〓\n●活动期间，限定5星角色「空月归乡·哥伦比娅(水)」的祈愿获取概率将大幅提升！\n●活动期间，4星角色「系风攘影·雅珂达(风)」「深黯的谜烟·欧洛伦(雷)」「衡明知度·赛索斯(雷)」的祈愿获取概率将大幅提升！\n※ 以上角色中，限定角色不会进入「奔行世间」常驻祈愿。\n※ 本祈愿属于「角色活动祈愿」，「角色活动祈愿」和「角色活动祈愿-2」的祈愿次数保底完全共享，会一直共同累计在「角色活动祈愿」和「角色活动祈愿-2」中，与其他祈愿的祈愿次数保底相互独立计算，互不影响。\n※ 祈愿开启期间，还将开启相应的「且试身手」角色试用活动，旅行者可以使用包含试用角色的固定阵容进入指定的关卡进行体验，挑战成功后即可获得对应奖励！\n\n※ 更多祈愿信息可点击祈愿界面左下角【详情】按钮进行查询。\n\nsource @YuanShen",
    "content": "「伴月同眠」祈愿：「空月归乡·哥伦比娅(水)」概率UP！\n\n活动期间，旅行者可以在活动祈愿中获得更多角色与武器，组建强大的队伍！\n \n〓祈愿介绍〓\n●活动期间，限定5星角色「空月归乡·哥伦比娅(水)」的祈愿获取概率将大幅提升！\n●活动期间，4星角色「系风攘影·雅珂达(风)」「深黯的谜烟·欧洛伦(雷)」「衡明知度·赛索斯(雷)」的祈愿获取概率将大幅提升！\n※ 以上角色中，限定角色不会进入「奔行世间」常驻祈愿。\n※ 本祈愿属于「角色活动祈愿」，「角色活动祈愿」和「角色活动祈愿-2」的祈愿次数保底完全共享，会一直共同累计在「角色活动祈愿」和「角色活动祈愿-2」中，与其他祈愿的祈愿次数保底相互独立计算，互不影响。\n※ 祈愿开启期间，还将开启相应的「且试身手」角色试用活动，旅行者可以使用包含试用角色的固定阵容进入指定的关卡进行体验，挑战成功后即可获得对应奖励！\n\n※ 更多祈愿信息可点击祈愿界面左下角【详情】按钮进行查询。\n\nsource @YuanShen",
    "image": "https://cora.jackie3137.xyz/f/8e6195071deec0c2f0db/Thunder%20File%20To%20Link_20260716080218.jpg",
    "images": [
      "https://cora.jackie3137.xyz/f/8e6195071deec0c2f0db/Thunder%20File%20To%20Link_20260716080218.jpg",
      "https://cora.jackie3137.xyz/f/1cea18c1eeedc36e9fbf/Thunder%20File%20To%20Link_20260716080448.jpg"
    ],
    "videos": [],
    "category": "活动",
    "important": false,
    "pinOrder": 999999,
    "pinExpiry": ""
  },
  {
    "id": 8028,
    "date": "2026-07-16",
    "time": "2026-07-16 07:00:33",
    "channel": "@MCKURO",
    "title": "「致予新世界-巡回演唱会礼包」限时上架\n\n漂泊者届时可前往游戏内【商城】-【礼包中心】查看详情。\n也",
    "text": "「致予新世界-巡回演唱会礼包」限时上架\n\n漂泊者届时可前往游戏内【商城】-【礼包中心】查看详情。\n也可在漂泊者的【角色服饰】界面进行饰品的预览。\n\n✦上架时间✦\n2026年7月19日20:30 ~ 2026年8月20日03:59（UTC+8）\n\n✦礼包说明✦\n「致予新世界-巡回演唱会礼包」\n售价：98 RMB\n礼包内容：「爪垫指挥家」*1（漂泊者饰品）、「献给夜空的返场」*1（羁旅印章）、星声*500\n\n※致予新世界-巡回演唱会礼包可以通过兑换「致予新世界」演唱会随票赠送的兑换码，或者购买游戏内商城对应限时礼包获得。\n※每位漂泊者可至多成功获取1次「致予新世界-巡回演唱会礼包」。通过任一途径成功获得过「致予新世界-巡回演唱会礼包」的漂泊者，将无法通过其他途径重复获取该礼包。\n※「爪垫指挥家」无法与漂泊者同一位置的其他饰品同时装配，还请注意。\n\nsource @MCKURO",
    "content": "「致予新世界-巡回演唱会礼包」限时上架\n\n漂泊者届时可前往游戏内【商城】-【礼包中心】查看详情。\n也可在漂泊者的【角色服饰】界面进行饰品的预览。\n\n✦上架时间✦\n2026年7月19日20:30 ~ 2026年8月20日03:59（UTC+8）\n\n✦礼包说明✦\n「致予新世界-巡回演唱会礼包」\n售价：98 RMB\n礼包内容：「爪垫指挥家」*1（漂泊者饰品）、「献给夜空的返场」*1（羁旅印章）、星声*500\n\n※致予新世界-巡回演唱会礼包可以通过兑换「致予新世界」演唱会随票赠送的兑换码，或者购买游戏内商城对应限时礼包获得。\n※每位漂泊者可至多成功获取1次「致予新世界-巡回演唱会礼包」。通过任一途径成功获得过「致予新世界-巡回演唱会礼包」的漂泊者，将无法通过其他途径重复获取该礼包。\n※「爪垫指挥家」无法与漂泊者同一位置的其他饰品同时装配，还请注意。\n\nsource @MCKURO",
    "image": "https://cora.jackie3137.xyz/f/aeec527f640a8281dc28/Thunder%20File%20To%20Link_20260716070045.jpg",
    "images": [
      "https://cora.jackie3137.xyz/f/aeec527f640a8281dc28/Thunder%20File%20To%20Link_20260716070045.jpg",
      "https://cora.jackie3137.xyz/f/040afca8e76477347d12/Thunder%20File%20To%20Link_20260716070135.jpg"
    ],
    "videos": [
      "https://cora.jackie3137.xyz/f/1be65baaacb1b6fef6de/f7c4ed11bcd047ac866cd302a9647b2620260716.mp4",
      "https://cora.jackie3137.xyz/f/c14fbdc930c0e06a437a/01cd6e0e3fe44e8bb4714b290cdc491520260716.mp4"
    ],
    "category": "活动",
    "important": false,
    "pinOrder": 999999,
    "pinExpiry": ""
  },
  {
    "id": 6658,
    "date": "2026-07-16",
    "time": "2026-07-16 04:06:12",
    "channel": "@YUANSHEN",
    "title": "@YUANSHEN",
    "text": "",
    "content": "",
    "image": "https://cora.jackie3137.xyz/f/44398f88e32c1524caec/Thunder%20File%20To%20Link_20260716040807.jpg",
    "images": [
      "https://cora.jackie3137.xyz/f/44398f88e32c1524caec/Thunder%20File%20To%20Link_20260716040807.jpg",
      "https://cora.jackie3137.xyz/f/db1eef97fa6d520c261c/Thunder%20File%20To%20Link_20260716041227.jpg",
      "https://cora.jackie3137.xyz/f/646fa6f2791639c15c43/Thunder%20File%20To%20Link_20260716041548.jpg",
      "https://cora.jackie3137.xyz/f/e4d3fda2b33b6d66c185/Thunder%20File%20To%20Link_20260716041919.jpg",
      "https://cora.jackie3137.xyz/f/d325106bf8ea3bae3ecd/Thunder%20File%20To%20Link_20260716042150.jpg",
      "https://cora.jackie3137.xyz/f/eef9f8fff1af2a58df66/Thunder%20File%20To%20Link_20260716042432.jpg",
      "https://cora.jackie3137.xyz/f/d5c7675f6388307ab276/Thunder%20File%20To%20Link_20260716042612.jpg",
      "https://cora.jackie3137.xyz/f/3ac9f03a790e3c81d6cd/Thunder%20File%20To%20Link_20260716042804.jpg",
      "https://cora.jackie3137.xyz/f/61febb9c0fcbc88912fc/Thunder%20File%20To%20Link_20260716042854.jpg",
      "https://cora.jackie3137.xyz/f/1701e1c82704123d864e/Thunder%20File%20To%20Link_20260716042944.jpg"
    ],
    "videos": [],
    "category": "活动",
    "important": false,
    "pinOrder": 999999,
    "pinExpiry": ""
  },
  {
    "id": 7997,
    "date": "2026-07-13",
    "time": "2026-07-13 10:08:32",
    "channel": "@MCKURO",
    "title": "✦ 「致予新世界」倒计时3天✦\n\n“准备好了吗？”\n\n《鸣潮》巡回演唱会「致予新世界」将于7月16日",
    "text": "✦ 「致予新世界」倒计时3天✦\n\n“准备好了吗？”\n\n《鸣潮》巡回演唱会「致予新世界」将于7月16日~7月18日在上海浦发银行东方体育中心开启演出！\n\nsource @MCKURO",
    "content": "✦ 「致予新世界」倒计时3天✦\n\n“准备好了吗？”\n\n《鸣潮》巡回演唱会「致予新世界」将于7月16日~7月18日在上海浦发银行东方体育中心开启演出！\n\nsource @MCKURO",
    "image": "https://cora.jackie3137.xyz/f/f9539e60f9a7cea1a33f/Thunder%20File%20To%20Link_20260713100925.jpg",
    "images": [
      "https://cora.jackie3137.xyz/f/f9539e60f9a7cea1a33f/Thunder%20File%20To%20Link_20260713100925.jpg"
    ],
    "videos": [],
    "category": "活动",
    "important": false,
    "pinOrder": 999999,
    "pinExpiry": ""
  },
  {
    "id": 129915,
    "date": "2026-07-13",
    "time": "2026-07-13 10:05:12",
    "channel": "@REVERSE1999CN",
    "title": "#重返未来1999# #重返未来原子之心联动# #重返未来联动# 【重返切洛梅】即将开启！ 欢迎来到",
    "text": "#重返未来1999# #重返未来原子之心联动# #重返未来联动# 【重返切洛梅】即将开启！ 欢迎来到，3826号设施。 ▶▶活动时间◀◀ 7/23 10:00 - 8/13 4:59 ▶▶开启...\n\n#重返未来1999# #重返未来原子之心联动# #重返未来联动# \n【重返切洛梅】即将开启！\n欢迎来到，3826号设施。\n\n▶▶活动时间◀◀\n7/23 10:00 - 8/13 4:59\n\n▶▶开启条件◀◀\n通关活动正篇PD.16「原子观照」\n\n▶▶玩法说明◀◀\n※前往探索3826号设施内的数个地标，处理局部失控或解决技术难题。\n※消耗神经聚合物，即可解锁、强化聚合物手套的各种能力，在战斗中提供巨大增益。\n※探索过程中收集到的历史、角色等信息将收录在【公开档案】中以供查看。\n\n▶▶主要奖励◀◀\n宽檐帽主题衣着「思维驾驶者」、全新满增幅6星心相 - 「科学编舞法」、联动纪念头像「抓住未来」、心绪之实·科学编舞法（使用后可将心相「科学编舞法」提升至满级）\n            长图\n               收起 查看大图 向左旋转 向右旋转           \n        重返未来：1999\n       \n          游戏\n         \n          角色扮演/策略/卡牌\n         \n        3.8活动剧情《世纪末尺度》正式上映！注册送超100抽及自选范围六星角色\n       \n        进入\n       \n\n专栏链接：https://www.bilibili.com/opus/1224488306334498825",
    "content": "#重返未来1999# #重返未来原子之心联动# #重返未来联动# 【重返切洛梅】即将开启！ 欢迎来到，3826号设施。 ▶▶活动时间◀◀ 7/23 10:00 - 8/13 4:59 ▶▶开启...\n\n#重返未来1999# #重返未来原子之心联动# #重返未来联动# \n【重返切洛梅】即将开启！\n欢迎来到，3826号设施。\n\n▶▶活动时间◀◀\n7/23 10:00 - 8/13 4:59\n\n▶▶开启条件◀◀\n通关活动正篇PD.16「原子观照」\n\n▶▶玩法说明◀◀\n※前往探索3826号设施内的数个地标，处理局部失控或解决技术难题。\n※消耗神经聚合物，即可解锁、强化聚合物手套的各种能力，在战斗中提供巨大增益。\n※探索过程中收集到的历史、角色等信息将收录在【公开档案】中以供查看。\n\n▶▶主要奖励◀◀\n宽檐帽主题衣着「思维驾驶者」、全新满增幅6星心相 - 「科学编舞法」、联动纪念头像「抓住未来」、心绪之实·科学编舞法（使用后可将心相「科学编舞法」提升至满级）\n            长图\n               收起 查看大图 向左旋转 向右旋转           \n        重返未来：1999\n       \n          游戏\n         \n          角色扮演/策略/卡牌\n         \n        3.8活动剧情《世纪末尺度》正式上映！注册送超100抽及自选范围六星角色\n       \n        进入\n       \n\n专栏链接：https://www.bilibili.com/opus/1224488306334498825",
    "image": "https://cora.jackie3137.xyz/f/1553ee6edb88df4253bc/Thunder%20File%20To%20Link_20260713100625.jpg",
    "images": [
      "https://cora.jackie3137.xyz/f/1553ee6edb88df4253bc/Thunder%20File%20To%20Link_20260713100625.jpg",
      "https://cora.jackie3137.xyz/f/e1a02f7e5f41cbb64b91/Thunder%20File%20To%20Link_20260703101249.jpg"
    ],
    "videos": [],
    "category": "活动",
    "important": false,
    "pinOrder": 999999,
    "pinExpiry": ""
  },
  {
    "id": 7996,
    "date": "2026-07-13",
    "time": "2026-07-13 10:06:06",
    "channel": "@MCKURO",
    "title": "《鸣潮》巡回演唱会「致予新世界」线上直播将于7月18日19:05开启！\n\n《鸣潮》巡回演唱会「致予新",
    "text": "《鸣潮》巡回演唱会「致予新世界」线上直播将于7月18日19:05开启！\n\n《鸣潮》巡回演唱会「致予新世界」线上直播将于7月18日19:05开启！\n本次线上直播将在《鸣潮》bilibili官方直播间播出，欢迎漂泊者准时收看！\n\nsource @MCKURO",
    "content": "《鸣潮》巡回演唱会「致予新世界」线上直播将于7月18日19:05开启！\n\n《鸣潮》巡回演唱会「致予新世界」线上直播将于7月18日19:05开启！\n本次线上直播将在《鸣潮》bilibili官方直播间播出，欢迎漂泊者准时收看！\n\nsource @MCKURO",
    "image": "https://cora.jackie3137.xyz/f/00fd5ca91e6bccd5656d/Thunder%20File%20To%20Link_20260713100715.jpg",
    "images": [
      "https://cora.jackie3137.xyz/f/00fd5ca91e6bccd5656d/Thunder%20File%20To%20Link_20260713100715.jpg"
    ],
    "videos": [],
    "category": "活动",
    "important": false,
    "pinOrder": 999999,
    "pinExpiry": ""
  },
  {
    "id": 129917,
    "date": "2026-07-13",
    "time": "2026-07-13 10:05:18",
    "channel": "@REVERSE1999CN",
    "title": "重返未来1999\n\n#重返未来1999# #重返未来原子之心联动# #重返未来联动# \n【重返切洛梅",
    "text": "重返未来1999\n\n#重返未来1999# #重返未来原子之心联动# #重返未来联动# \n【重返切洛梅】即将开启！\n欢迎来到，3826号设施。\n\n▶▶活动时间◀◀\n7/23 10:00 - 8/13 4:59\n\n▶▶开启条件◀◀\n通关活动正篇PD.16「原子观照」\n\n▶▶玩法说明◀◀\n※前往探索3826号设施内的数个地标，处理局部失控或解决技术难题。\n※消耗神经聚合物，即可解锁、强化聚合物手套的各种能力，在战斗中提供巨大增益。\n※探索过程中收集到的历史、角色等信息将收录在【公开档案】中以供查看。\n\n▶▶主要奖励◀◀\n宽檐帽主题衣着「思维驾驶者」、全新满增幅6星心相 - 「科学编舞法」、联动纪念头像「抓住未来」、心绪之实·科学编舞法（使用后可将心相「科学编舞法」提升至满级）\n\n\n图文地址：https://www.bilibili.com/opus/1224488306334498825",
    "content": "重返未来1999\n\n#重返未来1999# #重返未来原子之心联动# #重返未来联动# \n【重返切洛梅】即将开启！\n欢迎来到，3826号设施。\n\n▶▶活动时间◀◀\n7/23 10:00 - 8/13 4:59\n\n▶▶开启条件◀◀\n通关活动正篇PD.16「原子观照」\n\n▶▶玩法说明◀◀\n※前往探索3826号设施内的数个地标，处理局部失控或解决技术难题。\n※消耗神经聚合物，即可解锁、强化聚合物手套的各种能力，在战斗中提供巨大增益。\n※探索过程中收集到的历史、角色等信息将收录在【公开档案】中以供查看。\n\n▶▶主要奖励◀◀\n宽檐帽主题衣着「思维驾驶者」、全新满增幅6星心相 - 「科学编舞法」、联动纪念头像「抓住未来」、心绪之实·科学编舞法（使用后可将心相「科学编舞法」提升至满级）\n\n\n图文地址：https://www.bilibili.com/opus/1224488306334498825",
    "image": "https://cora.jackie3137.xyz/f/44c9d53b32128f384b12/Thunder%20File%20To%20Link_20260713100519.jpg",
    "images": [
      "https://cora.jackie3137.xyz/f/44c9d53b32128f384b12/Thunder%20File%20To%20Link_20260713100519.jpg"
    ],
    "videos": [],
    "category": "活动",
    "important": false,
    "pinOrder": 999999,
    "pinExpiry": ""
  },
  {
    "id": 16149,
    "date": "2026-07-13",
    "time": "2026-07-13 07:03:14",
    "channel": "@ANIME_NEWS_LATEST",
    "title": "💫\"Black Clover\" TV Anime Season 2 character design",
    "text": "💫\"Black Clover\" TV Anime Season 2 character design: Asta [Devil Union, Demon-Slasher]💫\n\nBroadcasting begins in October.",
    "content": "💫\"Black Clover\" TV Anime Season 2 character design: Asta [Devil Union, Demon-Slasher]💫\n\nBroadcasting begins in October.",
    "image": "https://cora.jackie3137.xyz/f/0ebcea90fd8748130a0f/Thunder%20File%20To%20Link_20260713070643.jpg",
    "images": [
      "https://cora.jackie3137.xyz/f/0ebcea90fd8748130a0f/Thunder%20File%20To%20Link_20260713070643.jpg",
      "https://cora.jackie3137.xyz/f/c7449dae2ebdb761fac8/Thunder%20File%20To%20Link_20260713070733.jpg"
    ],
    "videos": [],
    "category": "预告资讯",
    "important": false,
    "pinOrder": 999999,
    "pinExpiry": ""
  },
  {
    "id": 16150,
    "date": "2026-07-13",
    "time": "2026-07-13 07:03:17",
    "channel": "@ANIME_NEWS_LATEST",
    "title": "💫\"MOB PSYCHO 100\" Anime 10th Anniversary Special V",
    "text": "💫\"MOB PSYCHO 100\" Anime 10th Anniversary Special Video.💫",
    "content": "💫\"MOB PSYCHO 100\" Anime 10th Anniversary Special Video.💫",
    "image": "https://cora.jackie3137.xyz/f/bf5432dc892a0904a69d/1BtNlIiy_uR20A_remux.mp4",
    "images": [],
    "videos": [
      "https://cora.jackie3137.xyz/f/bf5432dc892a0904a69d/1BtNlIiy_uR20A_remux.mp4"
    ],
    "category": "预告资讯",
    "important": false,
    "pinOrder": 999999,
    "pinExpiry": ""
  },
  {
    "id": 16147,
    "date": "2026-07-13",
    "time": "2026-07-13 07:03:13",
    "channel": "@ANIME_NEWS_LATEST",
    "title": "💫\"The Eternal Fool's Words of Wisdom: A Pawsitivel",
    "text": "💫\"The Eternal Fool's Words of Wisdom: A Pawsitively Fantastic Adventure\" TV anime teaser PV.💫\n\nBroadcasting begins in January.",
    "content": "💫\"The Eternal Fool's Words of Wisdom: A Pawsitively Fantastic Adventure\" TV anime teaser PV.💫\n\nBroadcasting begins in January.",
    "image": "https://cora.jackie3137.xyz/f/14ab2a87c5dee49f7865/UuvnAiM7f_Clkw_remux.mp4",
    "images": [],
    "videos": [
      "https://cora.jackie3137.xyz/f/14ab2a87c5dee49f7865/UuvnAiM7f_Clkw_remux.mp4"
    ],
    "category": "预告资讯",
    "important": false,
    "pinOrder": 999999,
    "pinExpiry": ""
  }
]